{
  "incidentCount": {
    "SUSP CIRCUMSTANCE": 17784,
    "TRAFFIC STOP": 5034,
    "SIMPLE ASSAULT": 17284,
    "ARGUMENT FAMILY": 9878,
    "DUI": 16696,
    "MISC SERVICE CALL": 46546,
    "TRAFFIC COMPLAINT": 7806,
    "LOUD PARTY": 894,
    "BURGLARY": 13994,
    "MISC PUB": 75306,
    "FOLLOW UP": 51830,
    "UNATTENDED DEATH": 19940,
    "ICF/SCF": 9074,
    "HARASSMENT": 15203,
    "THREATENING": 11782,
    "PROPERTY DAMAGE": 20661,
    "VEH TOWED": 46450,
    "ALARM CALL": 5641,
    "TRESPASS WARN": 12294,
    "NUISANCE COMPLAINT": 23119,
    "ARGUMENT": 15906,
    "MISSING PERSON CXL": 705,
    "MVC VEH TOWED": 22477,
    "MVC": 53114,
    "ROBBERY": 6361,
    "LIC PLATE THEFT": 2205,
    "AUTO THEFT RECOVERY": 16833,
    "IDENTITY THEFT": 2361,
    "OVERDUE RENTAL VEH": 429,
    "LOST PROPERTY": 8041,
    "TRAFFIC CONTROL DEVICE": 2119,
    "PARKING VIOLATION": 33102,
    "UEMV": 15279,
    "MEDICAL ASSIST": 8620,
    "THEFT": 50804,
    "BURGLARY VEH TAKEN": 648,
    "TRESPASS": 10205,
    "AUTO THEFT": 19840,
    "STALLED/HAZARD VEH": 5324,
    "ORDER VIOLATION": 8011,
    "PEDD/SOLIC NUISANCE": 64,
    "ANIMAL NOISE": 2209,
    "SUSP VEH": 2171,
    "DEFIB CALL": 3162,
    "RECKLESS ENDANGERING": 890,
    "AGGRAVATED ASSAULT": 10865,
    "MISSING PERSON": 3948,
    "WARRANT ARREST": 29971,
    "FOUND PROPERTY": 3467,
    "MISC CRIME OFFENSE": 9683,
    "DROPPED CALL": 2765,
    "ATTENDED DEATH": 2066,
    "RUNAWAY": 6601,
    "FRAUD": 12501,
    "FAMILY OFF/NEG": 31269,
    "COUNTERFEIT/FORGERY": 2437,
    "BURGLARY VEH CXL": 476,
    "TRO INITIAL": 664,
    "HAZARDOUS DRIVER": 2160,
    "STALLED VEH": 696,
    "WEAPONS": 2556,
    "CUSTODIAL INTERFERENCE": 972,
    "DISORDERLY CONDUCT": 5046,
    "SUSP PERSON": 4309,
    "DRUGS/NARCOTICS": 5059,
    "TRAFFIC INCIDENT": 2340,
    "GRAFFITI": 1017,
    "JUVENILE NUISANCE": 725,
    "FIREWORKS VIOLATION": 2226,
    "RUNAWAY CXL": 5739,
    "DRUNK NUISANCE": 529,
    "NOISE COMPLAINT": 7225,
    "SEX ASSAULT": 3533,
    "CONSTRUCTION NOISE": 250,
    "ARGUMENT LANDLORD TENANT": 241,
    "LIQUOR LAW": 1927,
    "FIRE CALL": 3564,
    "OVERDUE RENTAL CXL": 358,
    "ATTEMPTED SUICIDE": 877,
    "RAPE": 2485,
    "KIDNAPPING": 481,
    "TRAFFIC ARREST/CITATION": 3366,
    "DRONE NUISANCE": 50,
    "INDECENT EXPOSURE": 1161,
    "LIC PLATE THEFT CXL": 226,
    "LPROP LIC PLATE": 415,
    "ARSON": 1117,
    "ROBBERY VEH CXL": 454,
    "FAMILY OFF/NEG WARN": 297,
    "DUST/ECOL NUISANCE": 67,
    "SMOKE/FIRE NUISANCE": 283,
    "ARGUMENT NON FAMILY": 205,
    "ROBBERY VEH TAKEN": 699,
    "DELINQUENT JUVENILE": 148,
    "HOLD UP ALARM": 94,
    "SUICIDE": 87,
    "VEH NOISE": 244,
    "TRUANCY": 241,
    "PROSTITUTION": 89,
    "EXTRADITION VIOLATION": 219,
    "LPROP LIC PLATE CXL": 18,
    "BOMB THREAT": 113,
    "ESCAPEE": 127,
    "ESCAPEE CXL": 91,
    "HOMICIDE": 712,
    "GAMBLING": 59,
    "AWOL": 7,
    "RESIDENCE CHECK": 1
  },
  "cityCount": {
    "ALA MOANA": 19538,
    "WAIKIKI": 75684,
    "KALIHI": 73461,
    "MOANALUA": 2016,
    "EWA BEACH": 44255,
    "MILILANI": 24398,
    "KAILUA": 34506,
    "AIEA": 36315,
    "LAIE": 5081,
    "HONOLULU": 66292,
    "WAIPAHU": 32885,
    "MAKIKI": 15156,
    "KAPOLEI": 28736,
    "PEARL CITY": 26061,
    "WAIANAE": 25445,
    "HAWAII KAI": 14656,
    "KAPAHULU": 10078,
    "WAIMANALO": 10628,
    "MAPUNAPUNA": 5091,
    "MAKAKILO": 7505,
    "AIRPORT": 7647,
    "KAHALA": 5977,
    "SUNSET": 7749,
    "KANEOHE": 36180,
    "MCCULLY": 33281,
    "KAIMUKI": 25600,
    "DOWNTOWN": 27308,
    "MANOA": 13182,
    "MAKAHA": 11382,
    "WAIALAE": 3393,
    "WAHIAWA": 24414,
    "MAILI": 9291,
    "KAHUKU": 7044,
    "AINA HAINA": 5539,
    "NANAKULI": 14535,
    "WAIPIO": 11575,
    "KAKAAKO": 3732,
    "SALT LAKE": 8748,
    "WAIALUA": 3712,
    "KAHALUU": 4599,
    "MOANALUA V": 6298,
    "KALAELOA": 5806,
    "NUUANU": 14056,
    "MOKULEIA": 3751,
    "HAUULA": 4393,
    "PUNALUU": 2599,
    "KUNIA": 1401,
    "KAAAWA": 3118,
    "HALEIWA": 8438,
    "PUNCHBOWL": 8191,
    "ALIAMANU": 2618,
    "MALOELAP": 174,
    "SCHOFIELD": 1872,
    "MOANALUA T": 579,
    "TRIPLER": 905,
    "IROQUOIS": 3368,
    "HALSEY T": 325,
    "MCBH": 1093,
    "AMR": 504,
    "JB PEARL": 547,
    "FT SHAFTER": 197,
    "PC PEN": 450,
    "FT DERUSSY": 1006,
    "JB HICKAM": 661,
    "BELLOWS": 165,
    "\u0000": 1397,
    "HOKULANI": 161,
    "KAHUKU RNG": 15,
    "94 - NAME?": 411,
    "CATLIN PK": 183,
    "MCGREW PT": 99,
    "MILLER PK": 264,
    "RADFORD T": 449,
    "FORD ISL": 125,
    "\u00a0": 40,
    "HALE MOKU": 408,
    "HELEMANO": 393,
    "CAMP SMITH": 18,
    "SHAFT FLAT": 76,
    "MAKUA": 108,
    "MAKALAPA": 64,
    "RED HILL": 33,
    "NCTAMS PAC": 49,
    "HALAWA": 137,
    "MANANA": 62,
    "WHEELER": 1,
    "WHEELER AFB": 2,
    "WAIPIO PT": 4,
    "PUULOA": 10,
    "NAVMAG LLL": 15
  },
  "districtCount": {
    "District 1": 143026,
    "District 6": 76792,
    "District 5": 124833,
    "District 8": 151092,
    "District 2": 76079,
    "District 4": 109538,
    "District 3": 108391,
    "District 7": 109014,
    "\u00a0": 854,
    "Citywide": 86,
    "LE": 9
  }
}