{
  "incidentCount": {
    "SUSP CIRCUMSTANCE": 348,
    "TRAFFIC STOP": 108,
    "SIMPLE ASSAULT": 273,
    "ARGUMENT FAMILY": 201,
    "DUI": 303,
    "MISC SERVICE CALL": 814,
    "TRAFFIC COMPLAINT": 246,
    "LOUD PARTY": 36,
    "BURGLARY": 311,
    "MISC PUB": 1322,
    "FOLLOW UP": 944,
    "UNATTENDED DEATH": 322,
    "ICF/SCF": 170,
    "HARASSMENT": 276,
    "THREATENING": 193,
    "PROPERTY DAMAGE": 476,
    "VEH TOWED": 742,
    "ALARM CALL": 123,
    "TRESPASS WARN": 273,
    "NUISANCE COMPLAINT": 395,
    "ARGUMENT": 299,
    "MISSING PERSON CXL": 10,
    "MVC VEH TOWED": 338,
    "MVC": 853,
    "ROBBERY": 129,
    "LIC PLATE THEFT": 83,
    "AUTO THEFT RECOVERY": 363,
    "IDENTITY THEFT": 25,
    "OVERDUE RENTAL VEH": 9,
    "LOST PROPERTY": 92,
    "TRAFFIC CONTROL DEVICE": 65,
    "PARKING VIOLATION": 461,
    "UEMV": 389,
    "MEDICAL ASSIST": 125,
    "THEFT": 1156,
    "BURGLARY VEH TAKEN": 23,
    "TRESPASS": 132,
    "AUTO THEFT": 297,
    "STALLED/HAZARD VEH": 84,
    "ORDER VIOLATION": 125,
    "PEDD/SOLIC NUISANCE": 2,
    "ANIMAL NOISE": 41,
    "SUSP VEH": 48,
    "DEFIB CALL": 96,
    "RECKLESS ENDANGERING": 32,
    "AGGRAVATED ASSAULT": 196,
    "MISSING PERSON": 99,
    "WARRANT ARREST": 551,
    "FOUND PROPERTY": 69,
    "MISC CRIME OFFENSE": 145,
    "DROPPED CALL": 44,
    "ATTENDED DEATH": 41,
    "RUNAWAY": 84,
    "FRAUD": 213,
    "FAMILY OFF/NEG": 662,
    "COUNTERFEIT/FORGERY": 46,
    "BURGLARY VEH CXL": 38,
    "TRO INITIAL": 23,
    "HAZARDOUS DRIVER": 24,
    "STALLED VEH": 23,
    "WEAPONS": 48,
    "CUSTODIAL INTERFERENCE": 30,
    "DISORDERLY CONDUCT": 74,
    "SUSP PERSON": 62,
    "DRUGS/NARCOTICS": 103,
    "TRAFFIC INCIDENT": 36,
    "GRAFFITI": 25,
    "JUVENILE NUISANCE": 16,
    "FIREWORKS VIOLATION": 467,
    "RUNAWAY CXL": 51,
    "DRUNK NUISANCE": 9,
    "NOISE COMPLAINT": 140,
    "SEX ASSAULT": 27,
    "CONSTRUCTION NOISE": 8,
    "ARGUMENT LANDLORD TENANT": 8,
    "LIQUOR LAW": 15,
    "FIRE CALL": 71,
    "OVERDUE RENTAL CXL": 12,
    "ATTEMPTED SUICIDE": 14,
    "RAPE": 48,
    "KIDNAPPING": 1,
    "TRAFFIC ARREST/CITATION": 20,
    "DRONE NUISANCE": 1,
    "INDECENT EXPOSURE": 16,
    "LIC PLATE THEFT CXL": 2,
    "LPROP LIC PLATE": 10,
    "ARSON": 59,
    "ROBBERY VEH CXL": 7,
    "FAMILY OFF/NEG WARN": 2,
    "DUST/ECOL NUISANCE": 7,
    "SMOKE/FIRE NUISANCE": 21,
    "ARGUMENT NON FAMILY": 3,
    "ROBBERY VEH TAKEN": 1,
    "DELINQUENT JUVENILE": 1,
    "HOLD UP ALARM": 1
  },
  "cityCount": {
    "ALA MOANA": 293,
    "WAIKIKI": 1191,
    "KALIHI": 1494,
    "MOANALUA": 17,
    "EWA BEACH": 929,
    "MILILANI": 449,
    "KAILUA": 703,
    "AIEA": 632,
    "LAIE": 74,
    "HONOLULU": 1164,
    "WAIPAHU": 648,
    "MAKIKI": 317,
    "KAPOLEI": 642,
    "PEARL CITY": 543,
    "WAIANAE": 528,
    "HAWAII KAI": 361,
    "KAPAHULU": 135,
    "WAIMANALO": 267,
    "MAPUNAPUNA": 64,
    "MAKAKILO": 139,
    "AIRPORT": 140,
    "KAHALA": 114,
    "SUNSET": 116,
    "KANEOHE": 797,
    "MCCULLY": 662,
    "KAIMUKI": 462,
    "DOWNTOWN": 558,
    "MANOA": 222,
    "MAKAHA": 247,
    "WAIALAE": 109,
    "WAHIAWA": 409,
    "MAILI": 165,
    "KAHUKU": 117,
    "AINA HAINA": 96,
    "NANAKULI": 212,
    "WAIPIO": 221,
    "KAKAAKO": 45,
    "SALT LAKE": 110,
    "WAIALUA": 70,
    "KAHALUU": 129,
    "MOANALUA V": 55,
    "KALAELOA": 173,
    "NUUANU": 275,
    "MOKULEIA": 42,
    "HAUULA": 65,
    "PUNALUU": 58,
    "KUNIA": 39,
    "KAAAWA": 37,
    "HALEIWA": 109,
    "PUNCHBOWL": 155,
    "ALIAMANU": 19,
    "MALOELAP": 2,
    "SCHOFIELD": 29,
    "MOANALUA T": 8,
    "TRIPLER": 7,
    "IROQUOIS": 39,
    "HALSEY T": 4,
    "MCBH": 4,
    "AMR": 7,
    "JB PEARL": 7,
    "FT SHAFTER": 2,
    "PC PEN": 6,
    "FT DERUSSY": 21,
    "JB HICKAM": 13,
    "BELLOWS": 13,
    "\u0000": 33,
    "HOKULANI": 2,
    "KAHUKU RNG": 1,
    "94 - NAME?": 1,
    "CATLIN PK": 2,
    "MCGREW PT": 2,
    "MILLER PK": 2,
    "RADFORD T": 1,
    "FORD ISL": 3
  },
  "districtCount": {
    "District 1": 2579,
    "District 6": 1213,
    "District 5": 2231,
    "District 8": 3090,
    "District 2": 1253,
    "District 4": 2268,
    "District 3": 2061,
    "District 7": 2118,
    "\u00a0": 14
  }
}