{
  "incidentCount": {
    "SUSP CIRCUMSTANCE": 17969,
    "TRAFFIC STOP": 5068,
    "SIMPLE ASSAULT": 17457,
    "ARGUMENT FAMILY": 9997,
    "DUI": 16840,
    "MISC SERVICE CALL": 46949,
    "TRAFFIC COMPLAINT": 7871,
    "LOUD PARTY": 900,
    "BURGLARY": 14115,
    "MISC PUB": 75916,
    "FOLLOW UP": 52225,
    "UNATTENDED DEATH": 20098,
    "ICF/SCF": 9160,
    "HARASSMENT": 15348,
    "THREATENING": 11891,
    "PROPERTY DAMAGE": 20791,
    "VEH TOWED": 46910,
    "ALARM CALL": 5694,
    "TRESPASS WARN": 12425,
    "NUISANCE COMPLAINT": 23311,
    "ARGUMENT": 16015,
    "MISSING PERSON CXL": 708,
    "MVC VEH TOWED": 22643,
    "MVC": 53640,
    "ROBBERY": 6428,
    "LIC PLATE THEFT": 2218,
    "AUTO THEFT RECOVERY": 16952,
    "IDENTITY THEFT": 2372,
    "OVERDUE RENTAL VEH": 446,
    "LOST PROPERTY": 8122,
    "TRAFFIC CONTROL DEVICE": 2123,
    "PARKING VIOLATION": 33365,
    "UEMV": 15386,
    "MEDICAL ASSIST": 8704,
    "THEFT": 51137,
    "BURGLARY VEH TAKEN": 648,
    "TRESPASS": 10341,
    "AUTO THEFT": 20001,
    "STALLED/HAZARD VEH": 5370,
    "ORDER VIOLATION": 8086,
    "PEDD/SOLIC NUISANCE": 67,
    "ANIMAL NOISE": 2235,
    "SUSP VEH": 2182,
    "DEFIB CALL": 3201,
    "RECKLESS ENDANGERING": 901,
    "AGGRAVATED ASSAULT": 10944,
    "MISSING PERSON": 3987,
    "WARRANT ARREST": 30142,
    "FOUND PROPERTY": 3488,
    "MISC CRIME OFFENSE": 9809,
    "DROPPED CALL": 2792,
    "ATTENDED DEATH": 2079,
    "RUNAWAY": 6660,
    "FRAUD": 12583,
    "FAMILY OFF/NEG": 31620,
    "COUNTERFEIT/FORGERY": 2444,
    "BURGLARY VEH CXL": 479,
    "TRO INITIAL": 667,
    "HAZARDOUS DRIVER": 2168,
    "STALLED VEH": 701,
    "WEAPONS": 2569,
    "CUSTODIAL INTERFERENCE": 976,
    "DISORDERLY CONDUCT": 5092,
    "SUSP PERSON": 4345,
    "DRUGS/NARCOTICS": 5108,
    "TRAFFIC INCIDENT": 2357,
    "GRAFFITI": 1019,
    "JUVENILE NUISANCE": 729,
    "FIREWORKS VIOLATION": 2278,
    "RUNAWAY CXL": 5793,
    "DRUNK NUISANCE": 532,
    "NOISE COMPLAINT": 7277,
    "SEX ASSAULT": 3545,
    "CONSTRUCTION NOISE": 253,
    "ARGUMENT LANDLORD TENANT": 247,
    "LIQUOR LAW": 1929,
    "FIRE CALL": 3615,
    "OVERDUE RENTAL CXL": 359,
    "ATTEMPTED SUICIDE": 881,
    "RAPE": 2487,
    "KIDNAPPING": 483,
    "TRAFFIC ARREST/CITATION": 3394,
    "DRONE NUISANCE": 51,
    "INDECENT EXPOSURE": 1194,
    "LIC PLATE THEFT CXL": 226,
    "LPROP LIC PLATE": 415,
    "ARSON": 1159,
    "ROBBERY VEH CXL": 457,
    "FAMILY OFF/NEG WARN": 307,
    "DUST/ECOL NUISANCE": 67,
    "SMOKE/FIRE NUISANCE": 285,
    "ARGUMENT NON FAMILY": 207,
    "ROBBERY VEH TAKEN": 707,
    "DELINQUENT JUVENILE": 149,
    "HOLD UP ALARM": 95,
    "SUICIDE": 87,
    "VEH NOISE": 250,
    "TRUANCY": 242,
    "PROSTITUTION": 89,
    "EXTRADITION VIOLATION": 219,
    "LPROP LIC PLATE CXL": 18,
    "BOMB THREAT": 113,
    "ESCAPEE": 127,
    "ESCAPEE CXL": 91,
    "HOMICIDE": 712,
    "GAMBLING": 59,
    "AWOL": 7,
    "RESIDENCE CHECK": 1
  },
  "cityCount": {
    "ALA MOANA": 19666,
    "WAIKIKI": 76508,
    "KALIHI": 73930,
    "MOANALUA": 2033,
    "EWA BEACH": 44677,
    "MILILANI": 24624,
    "KAILUA": 34756,
    "AIEA": 36617,
    "LAIE": 5102,
    "HONOLULU": 66822,
    "WAIPAHU": 33183,
    "MAKIKI": 15230,
    "KAPOLEI": 29043,
    "PEARL CITY": 26354,
    "WAIANAE": 25725,
    "HAWAII KAI": 14759,
    "KAPAHULU": 10155,
    "WAIMANALO": 10731,
    "MAPUNAPUNA": 5136,
    "MAKAKILO": 7538,
    "AIRPORT": 7722,
    "KAHALA": 6019,
    "SUNSET": 7775,
    "KANEOHE": 36498,
    "MCCULLY": 33480,
    "KAIMUKI": 25896,
    "DOWNTOWN": 27560,
    "MANOA": 13330,
    "MAKAHA": 11485,
    "WAIALAE": 3419,
    "WAHIAWA": 24579,
    "MAILI": 9396,
    "KAHUKU": 7055,
    "AINA HAINA": 5595,
    "NANAKULI": 14665,
    "WAIPIO": 11696,
    "KAKAAKO": 3755,
    "SALT LAKE": 8839,
    "WAIALUA": 3733,
    "KAHALUU": 4662,
    "MOANALUA V": 6332,
    "KALAELOA": 5860,
    "NUUANU": 14188,
    "MOKULEIA": 3811,
    "HAUULA": 4417,
    "PUNALUU": 2623,
    "KUNIA": 1411,
    "KAAAWA": 3123,
    "HALEIWA": 8471,
    "PUNCHBOWL": 8255,
    "ALIAMANU": 2643,
    "MALOELAP": 174,
    "SCHOFIELD": 1887,
    "MOANALUA T": 580,
    "TRIPLER": 907,
    "IROQUOIS": 3388,
    "HALSEY T": 335,
    "MCBH": 1110,
    "AMR": 511,
    "JB PEARL": 557,
    "FT SHAFTER": 198,
    "PC PEN": 450,
    "FT DERUSSY": 1023,
    "JB HICKAM": 680,
    "BELLOWS": 165,
    "\u0000": 1405,
    "HOKULANI": 162,
    "KAHUKU RNG": 15,
    "94 - NAME?": 412,
    "CATLIN PK": 187,
    "MCGREW PT": 99,
    "MILLER PK": 265,
    "RADFORD T": 451,
    "FORD ISL": 125,
    "\u00a0": 40,
    "HALE MOKU": 410,
    "HELEMANO": 393,
    "CAMP SMITH": 18,
    "SHAFT FLAT": 77,
    "MAKUA": 108,
    "MAKALAPA": 64,
    "RED HILL": 33,
    "NCTAMS PAC": 49,
    "HALAWA": 137,
    "MANANA": 62,
    "WHEELER": 1,
    "WHEELER AFB": 2,
    "WAIPIO PT": 4,
    "PUULOA": 10,
    "NAVMAG LLL": 15
  },
  "districtCount": {
    "District 1": 144109,
    "District 6": 77633,
    "District 5": 125772,
    "District 8": 152547,
    "District 2": 76635,
    "District 4": 110374,
    "District 3": 109415,
    "District 7": 109952,
    "\u00a0": 859,
    "Citywide": 86,
    "LE": 9
  }
}