{
  "incidentCount": {
    "SUSP CIRCUMSTANCE": 11624,
    "TRAFFIC STOP": 3222,
    "SIMPLE ASSAULT": 11332,
    "ARGUMENT FAMILY": 6587,
    "DUI": 11023,
    "MISC SERVICE CALL": 31296,
    "TRAFFIC COMPLAINT": 5125,
    "LOUD PARTY": 592,
    "BURGLARY": 9651,
    "MISC PUB": 50953,
    "FOLLOW UP": 34073,
    "UNATTENDED DEATH": 13317,
    "ICF/SCF": 5877,
    "HARASSMENT": 10182,
    "THREATENING": 7491,
    "PROPERTY DAMAGE": 13968,
    "VEH TOWED": 29334,
    "ALARM CALL": 3779,
    "TRESPASS WARN": 8100,
    "NUISANCE COMPLAINT": 15280,
    "ARGUMENT": 10561,
    "MISSING PERSON CXL": 446,
    "MVC VEH TOWED": 14637,
    "MVC": 34363,
    "ROBBERY": 4073,
    "LIC PLATE THEFT": 1567,
    "AUTO THEFT RECOVERY": 11674,
    "IDENTITY THEFT": 1594,
    "OVERDUE RENTAL VEH": 289,
    "LOST PROPERTY": 5312,
    "TRAFFIC CONTROL DEVICE": 1493,
    "PARKING VIOLATION": 21147,
    "UEMV": 10661,
    "MEDICAL ASSIST": 5558,
    "THEFT": 33872,
    "BURGLARY VEH TAKEN": 456,
    "TRESPASS": 6024,
    "AUTO THEFT": 13290,
    "STALLED/HAZARD VEH": 3421,
    "ORDER VIOLATION": 5426,
    "PEDD/SOLIC NUISANCE": 47,
    "ANIMAL NOISE": 1443,
    "SUSP VEH": 1487,
    "DEFIB CALL": 2143,
    "RECKLESS ENDANGERING": 494,
    "AGGRAVATED ASSAULT": 6709,
    "MISSING PERSON": 2662,
    "WARRANT ARREST": 18931,
    "FOUND PROPERTY": 2248,
    "MISC CRIME OFFENSE": 5578,
    "DROPPED CALL": 1709,
    "ATTENDED DEATH": 1323,
    "RUNAWAY": 4318,
    "FRAUD": 8161,
    "FAMILY OFF/NEG": 19477,
    "COUNTERFEIT/FORGERY": 1601,
    "BURGLARY VEH CXL": 387,
    "TRO INITIAL": 441,
    "HAZARDOUS DRIVER": 1367,
    "STALLED VEH": 458,
    "WEAPONS": 1667,
    "CUSTODIAL INTERFERENCE": 670,
    "DISORDERLY CONDUCT": 3126,
    "SUSP PERSON": 2894,
    "DRUGS/NARCOTICS": 3358,
    "TRAFFIC INCIDENT": 1525,
    "GRAFFITI": 743,
    "JUVENILE NUISANCE": 468,
    "FIREWORKS VIOLATION": 1796,
    "RUNAWAY CXL": 3645,
    "DRUNK NUISANCE": 372,
    "NOISE COMPLAINT": 4750,
    "SEX ASSAULT": 2191,
    "CONSTRUCTION NOISE": 179,
    "ARGUMENT LANDLORD TENANT": 141,
    "LIQUOR LAW": 1099,
    "FIRE CALL": 2417,
    "OVERDUE RENTAL CXL": 220,
    "ATTEMPTED SUICIDE": 584,
    "RAPE": 1568,
    "KIDNAPPING": 346,
    "TRAFFIC ARREST/CITATION": 2032,
    "DRONE NUISANCE": 37,
    "INDECENT EXPOSURE": 685,
    "LIC PLATE THEFT CXL": 149,
    "LPROP LIC PLATE": 304,
    "ARSON": 754,
    "ROBBERY VEH CXL": 323,
    "FAMILY OFF/NEG WARN": 170,
    "DUST/ECOL NUISANCE": 44,
    "SMOKE/FIRE NUISANCE": 196,
    "ARGUMENT NON FAMILY": 139,
    "ROBBERY VEH TAKEN": 445,
    "DELINQUENT JUVENILE": 88,
    "HOLD UP ALARM": 63,
    "SUICIDE": 57,
    "VEH NOISE": 153,
    "TRUANCY": 154,
    "PROSTITUTION": 51,
    "EXTRADITION VIOLATION": 104,
    "LPROP LIC PLATE CXL": 7,
    "BOMB THREAT": 72,
    "ESCAPEE": 78,
    "ESCAPEE CXL": 44,
    "HOMICIDE": 522,
    "GAMBLING": 51,
    "AWOL": 7,
    "RESIDENCE CHECK": 1
  },
  "cityCount": {
    "ALA MOANA": 12852,
    "WAIKIKI": 46765,
    "KALIHI": 50051,
    "MOANALUA": 1162,
    "EWA BEACH": 29612,
    "MILILANI": 15820,
    "KAILUA": 23329,
    "AIEA": 24264,
    "LAIE": 3699,
    "HONOLULU": 42996,
    "WAIPAHU": 21963,
    "MAKIKI": 9385,
    "KAPOLEI": 18491,
    "PEARL CITY": 17545,
    "WAIANAE": 15113,
    "HAWAII KAI": 9980,
    "KAPAHULU": 6667,
    "WAIMANALO": 7148,
    "MAPUNAPUNA": 3720,
    "MAKAKILO": 5088,
    "AIRPORT": 5057,
    "KAHALA": 3822,
    "SUNSET": 5457,
    "KANEOHE": 23284,
    "MCCULLY": 21703,
    "KAIMUKI": 16347,
    "DOWNTOWN": 17262,
    "MANOA": 8317,
    "MAKAHA": 7738,
    "WAIALAE": 2337,
    "WAHIAWA": 15688,
    "MAILI": 6055,
    "KAHUKU": 4973,
    "AINA HAINA": 3567,
    "NANAKULI": 9515,
    "WAIPIO": 7863,
    "KAKAAKO": 2314,
    "SALT LAKE": 5603,
    "WAIALUA": 2637,
    "KAHALUU": 3037,
    "MOANALUA V": 3932,
    "KALAELOA": 4023,
    "NUUANU": 9707,
    "MOKULEIA": 2693,
    "HAUULA": 3243,
    "PUNALUU": 1852,
    "KUNIA": 961,
    "KAAAWA": 2158,
    "HALEIWA": 5902,
    "PUNCHBOWL": 5168,
    "ALIAMANU": 1705,
    "MALOELAP": 90,
    "SCHOFIELD": 1380,
    "MOANALUA T": 345,
    "TRIPLER": 568,
    "IROQUOIS": 2238,
    "HALSEY T": 213,
    "MCBH": 693,
    "AMR": 379,
    "JB PEARL": 338,
    "FT SHAFTER": 142,
    "PC PEN": 328,
    "FT DERUSSY": 585,
    "JB HICKAM": 368,
    "BELLOWS": 133,
    "\u0000": 794,
    "HOKULANI": 71,
    "KAHUKU RNG": 11,
    "94 - NAME?": 268,
    "CATLIN PK": 101,
    "MCGREW PT": 49,
    "MILLER PK": 160,
    "RADFORD T": 307,
    "FORD ISL": 72,
    "\u00a0": 38,
    "HALE MOKU": 252,
    "HELEMANO": 296,
    "CAMP SMITH": 14,
    "SHAFT FLAT": 28,
    "MAKUA": 92,
    "MAKALAPA": 44,
    "RED HILL": 18,
    "NCTAMS PAC": 19,
    "HALAWA": 81,
    "MANANA": 29,
    "WHEELER": 1,
    "WHEELER AFB": 2,
    "WAIPIO PT": 1,
    "PUULOA": 10,
    "NAVMAG LLL": 15
  },
  "districtCount": {
    "District 1": 91765,
    "District 6": 47438,
    "District 5": 84004,
    "District 8": 98325,
    "District 2": 50754,
    "District 4": 73587,
    "District 3": 72655,
    "District 7": 70992,
    "\u00a0": 567,
    "Citywide": 50,
    "LE": 6
  }
}