{
  "incidentCount": {
    "SUSP CIRCUMSTANCE": 775,
    "TRAFFIC STOP": 236,
    "SIMPLE ASSAULT": 733,
    "ARGUMENT FAMILY": 425,
    "DUI": 810,
    "MISC SERVICE CALL": 1968,
    "TRAFFIC COMPLAINT": 417,
    "LOUD PARTY": 71,
    "BURGLARY": 743,
    "MISC PUB": 3177,
    "FOLLOW UP": 2373,
    "UNATTENDED DEATH": 750,
    "ICF/SCF": 379,
    "HARASSMENT": 699,
    "THREATENING": 522,
    "PROPERTY DAMAGE": 1059,
    "VEH TOWED": 1794,
    "ALARM CALL": 276,
    "TRESPASS WARN": 626,
    "NUISANCE COMPLAINT": 969,
    "ARGUMENT": 702,
    "MISSING PERSON CXL": 24,
    "MVC VEH TOWED": 791,
    "MVC": 2036,
    "ROBBERY": 324,
    "LIC PLATE THEFT": 136,
    "AUTO THEFT RECOVERY": 827,
    "IDENTITY THEFT": 99,
    "OVERDUE RENTAL VEH": 24,
    "LOST PROPERTY": 315,
    "TRAFFIC CONTROL DEVICE": 111,
    "PARKING VIOLATION": 1171,
    "UEMV": 966,
    "MEDICAL ASSIST": 320,
    "THEFT": 2585,
    "BURGLARY VEH TAKEN": 55,
    "TRESPASS": 371,
    "AUTO THEFT": 804,
    "STALLED/HAZARD VEH": 181,
    "ORDER VIOLATION": 285,
    "PEDD/SOLIC NUISANCE": 3,
    "ANIMAL NOISE": 92,
    "SUSP VEH": 98,
    "DEFIB CALL": 174,
    "RECKLESS ENDANGERING": 77,
    "AGGRAVATED ASSAULT": 407,
    "MISSING PERSON": 189,
    "WARRANT ARREST": 1112,
    "FOUND PROPERTY": 169,
    "MISC CRIME OFFENSE": 354,
    "DROPPED CALL": 119,
    "ATTENDED DEATH": 78,
    "RUNAWAY": 240,
    "FRAUD": 425,
    "FAMILY OFF/NEG": 1182,
    "COUNTERFEIT/FORGERY": 110,
    "BURGLARY VEH CXL": 46,
    "TRO INITIAL": 32,
    "HAZARDOUS DRIVER": 64,
    "STALLED VEH": 31,
    "WEAPONS": 104,
    "CUSTODIAL INTERFERENCE": 55,
    "DISORDERLY CONDUCT": 179,
    "SUSP PERSON": 194,
    "DRUGS/NARCOTICS": 318,
    "TRAFFIC INCIDENT": 106,
    "GRAFFITI": 64,
    "JUVENILE NUISANCE": 26,
    "FIREWORKS VIOLATION": 541,
    "RUNAWAY CXL": 185,
    "DRUNK NUISANCE": 25,
    "NOISE COMPLAINT": 308,
    "SEX ASSAULT": 166,
    "CONSTRUCTION NOISE": 14,
    "ARGUMENT LANDLORD TENANT": 10,
    "LIQUOR LAW": 40,
    "FIRE CALL": 143,
    "OVERDUE RENTAL CXL": 14,
    "ATTEMPTED SUICIDE": 36,
    "RAPE": 100,
    "KIDNAPPING": 1,
    "TRAFFIC ARREST/CITATION": 56,
    "DRONE NUISANCE": 1,
    "INDECENT EXPOSURE": 28,
    "LIC PLATE THEFT CXL": 3,
    "LPROP LIC PLATE": 19,
    "ARSON": 113,
    "ROBBERY VEH CXL": 15,
    "FAMILY OFF/NEG WARN": 7,
    "DUST/ECOL NUISANCE": 9,
    "SMOKE/FIRE NUISANCE": 30,
    "ARGUMENT NON FAMILY": 5,
    "ROBBERY VEH TAKEN": 16,
    "DELINQUENT JUVENILE": 1,
    "HOLD UP ALARM": 3,
    "SUICIDE": 6,
    "VEH NOISE": 6,
    "TRUANCY": 2
  },
  "cityCount": {
    "ALA MOANA": 786,
    "WAIKIKI": 3000,
    "KALIHI": 3181,
    "MOANALUA": 47,
    "EWA BEACH": 1918,
    "MILILANI": 1001,
    "KAILUA": 1528,
    "AIEA": 1453,
    "LAIE": 201,
    "HONOLULU": 2900,
    "WAIPAHU": 1294,
    "MAKIKI": 691,
    "KAPOLEI": 1445,
    "PEARL CITY": 1227,
    "WAIANAE": 1100,
    "HAWAII KAI": 868,
    "KAPAHULU": 334,
    "WAIMANALO": 516,
    "MAPUNAPUNA": 169,
    "MAKAKILO": 266,
    "AIRPORT": 341,
    "KAHALA": 247,
    "SUNSET": 417,
    "KANEOHE": 1637,
    "MCCULLY": 1514,
    "KAIMUKI": 1071,
    "DOWNTOWN": 1291,
    "MANOA": 571,
    "MAKAHA": 513,
    "WAIALAE": 190,
    "WAHIAWA": 978,
    "MAILI": 334,
    "KAHUKU": 355,
    "AINA HAINA": 282,
    "NANAKULI": 636,
    "WAIPIO": 435,
    "KAKAAKO": 137,
    "SALT LAKE": 326,
    "WAIALUA": 221,
    "KAHALUU": 263,
    "MOANALUA V": 198,
    "KALAELOA": 303,
    "NUUANU": 582,
    "MOKULEIA": 127,
    "HAUULA": 196,
    "PUNALUU": 137,
    "KUNIA": 80,
    "KAAAWA": 134,
    "HALEIWA": 441,
    "PUNCHBOWL": 379,
    "ALIAMANU": 69,
    "MALOELAP": 2,
    "SCHOFIELD": 78,
    "MOANALUA T": 12,
    "TRIPLER": 21,
    "IROQUOIS": 106,
    "HALSEY T": 4,
    "MCBH": 16,
    "AMR": 30,
    "JB PEARL": 26,
    "FT SHAFTER": 10,
    "PC PEN": 14,
    "FT DERUSSY": 45,
    "JB HICKAM": 19,
    "BELLOWS": 14,
    "\u0000": 58,
    "HOKULANI": 2,
    "KAHUKU RNG": 1,
    "94 - NAME?": 14,
    "CATLIN PK": 2,
    "MCGREW PT": 2,
    "MILLER PK": 10,
    "RADFORD T": 3,
    "FORD ISL": 5,
    "\u00a0": 33,
    "HALE MOKU": 12,
    "HELEMANO": 3,
    "CAMP SMITH": 1,
    "SHAFT FLAT": 1,
    "MAKUA": 6
  },
  "districtCount": {
    "District 1": 6294,
    "District 6": 3048,
    "District 5": 5048,
    "District 8": 6653,
    "District 2": 3345,
    "District 4": 4999,
    "District 3": 4456,
    "District 7": 4968,
    "\u00a0": 68,
    "Citywide": 1
  }
}