{
  "incidentCount": {
    "SUSP CIRCUMSTANCE": 413,
    "TRAFFIC STOP": 131,
    "SIMPLE ASSAULT": 338,
    "ARGUMENT FAMILY": 238,
    "DUI": 341,
    "MISC SERVICE CALL": 1022,
    "TRAFFIC COMPLAINT": 290,
    "LOUD PARTY": 37,
    "BURGLARY": 397,
    "MISC PUB": 1720,
    "FOLLOW UP": 1156,
    "UNATTENDED DEATH": 381,
    "ICF/SCF": 202,
    "HARASSMENT": 350,
    "THREATENING": 308,
    "PROPERTY DAMAGE": 609,
    "VEH TOWED": 941,
    "ALARM CALL": 142,
    "TRESPASS WARN": 389,
    "NUISANCE COMPLAINT": 500,
    "ARGUMENT": 376,
    "MISSING PERSON CXL": 14,
    "MVC VEH TOWED": 419,
    "MVC": 1041,
    "ROBBERY": 179,
    "LIC PLATE THEFT": 96,
    "AUTO THEFT RECOVERY": 431,
    "IDENTITY THEFT": 38,
    "OVERDUE RENTAL VEH": 9,
    "LOST PROPERTY": 135,
    "TRAFFIC CONTROL DEVICE": 86,
    "PARKING VIOLATION": 598,
    "UEMV": 489,
    "MEDICAL ASSIST": 151,
    "THEFT": 1480,
    "BURGLARY VEH TAKEN": 23,
    "TRESPASS": 177,
    "AUTO THEFT": 376,
    "STALLED/HAZARD VEH": 106,
    "ORDER VIOLATION": 142,
    "PEDD/SOLIC NUISANCE": 3,
    "ANIMAL NOISE": 44,
    "SUSP VEH": 56,
    "DEFIB CALL": 105,
    "RECKLESS ENDANGERING": 33,
    "AGGRAVATED ASSAULT": 236,
    "MISSING PERSON": 117,
    "WARRANT ARREST": 588,
    "FOUND PROPERTY": 90,
    "MISC CRIME OFFENSE": 160,
    "DROPPED CALL": 62,
    "ATTENDED DEATH": 43,
    "RUNAWAY": 97,
    "FRAUD": 279,
    "FAMILY OFF/NEG": 734,
    "COUNTERFEIT/FORGERY": 73,
    "BURGLARY VEH CXL": 38,
    "TRO INITIAL": 27,
    "HAZARDOUS DRIVER": 30,
    "STALLED VEH": 24,
    "WEAPONS": 61,
    "CUSTODIAL INTERFERENCE": 32,
    "DISORDERLY CONDUCT": 86,
    "SUSP PERSON": 86,
    "DRUGS/NARCOTICS": 128,
    "TRAFFIC INCIDENT": 42,
    "GRAFFITI": 31,
    "JUVENILE NUISANCE": 16,
    "FIREWORKS VIOLATION": 497,
    "RUNAWAY CXL": 81,
    "DRUNK NUISANCE": 9,
    "NOISE COMPLAINT": 157,
    "SEX ASSAULT": 42,
    "CONSTRUCTION NOISE": 10,
    "ARGUMENT LANDLORD TENANT": 8,
    "LIQUOR LAW": 15,
    "FIRE CALL": 76,
    "OVERDUE RENTAL CXL": 12,
    "ATTEMPTED SUICIDE": 20,
    "RAPE": 54,
    "KIDNAPPING": 1,
    "TRAFFIC ARREST/CITATION": 24,
    "DRONE NUISANCE": 1,
    "INDECENT EXPOSURE": 17,
    "LIC PLATE THEFT CXL": 2,
    "LPROP LIC PLATE": 11,
    "ARSON": 86,
    "ROBBERY VEH CXL": 7,
    "FAMILY OFF/NEG WARN": 2,
    "DUST/ECOL NUISANCE": 7,
    "SMOKE/FIRE NUISANCE": 22,
    "ARGUMENT NON FAMILY": 3,
    "ROBBERY VEH TAKEN": 1,
    "DELINQUENT JUVENILE": 1,
    "HOLD UP ALARM": 1
  },
  "cityCount": {
    "ALA MOANA": 374,
    "WAIKIKI": 1520,
    "KALIHI": 1815,
    "MOANALUA": 20,
    "EWA BEACH": 1111,
    "MILILANI": 585,
    "KAILUA": 903,
    "AIEA": 736,
    "LAIE": 93,
    "HONOLULU": 1422,
    "WAIPAHU": 780,
    "MAKIKI": 374,
    "KAPOLEI": 734,
    "PEARL CITY": 668,
    "WAIANAE": 635,
    "HAWAII KAI": 446,
    "KAPAHULU": 175,
    "WAIMANALO": 283,
    "MAPUNAPUNA": 73,
    "MAKAKILO": 161,
    "AIRPORT": 190,
    "KAHALA": 142,
    "SUNSET": 173,
    "KANEOHE": 963,
    "MCCULLY": 831,
    "KAIMUKI": 601,
    "DOWNTOWN": 659,
    "MANOA": 288,
    "MAKAHA": 271,
    "WAIALAE": 116,
    "WAHIAWA": 496,
    "MAILI": 184,
    "KAHUKU": 147,
    "AINA HAINA": 137,
    "NANAKULI": 332,
    "WAIPIO": 258,
    "KAKAAKO": 46,
    "SALT LAKE": 161,
    "WAIALUA": 80,
    "KAHALUU": 166,
    "MOANALUA V": 71,
    "KALAELOA": 185,
    "NUUANU": 319,
    "MOKULEIA": 64,
    "HAUULA": 94,
    "PUNALUU": 81,
    "KUNIA": 53,
    "KAAAWA": 82,
    "HALEIWA": 151,
    "PUNCHBOWL": 194,
    "ALIAMANU": 22,
    "MALOELAP": 2,
    "SCHOFIELD": 45,
    "MOANALUA T": 8,
    "TRIPLER": 13,
    "IROQUOIS": 42,
    "HALSEY T": 4,
    "MCBH": 5,
    "AMR": 7,
    "JB PEARL": 11,
    "FT SHAFTER": 2,
    "PC PEN": 10,
    "FT DERUSSY": 21,
    "JB HICKAM": 13,
    "BELLOWS": 13,
    "\u0000": 33,
    "HOKULANI": 2,
    "KAHUKU RNG": 1,
    "94 - NAME?": 6,
    "CATLIN PK": 2,
    "MCGREW PT": 2,
    "MILLER PK": 7,
    "RADFORD T": 2,
    "FORD ISL": 3,
    "\u00a0": 33,
    "HALE MOKU": 5,
    "HELEMANO": 1,
    "CAMP SMITH": 1
  },
  "districtCount": {
    "District 1": 3127,
    "District 6": 1542,
    "District 5": 2745,
    "District 8": 3674,
    "District 2": 1639,
    "District 4": 2832,
    "District 3": 2468,
    "District 7": 2681,
    "\u00a0": 51
  }
}