{
  "incidentCount": {
    "SUSP CIRCUMSTANCE": 16997,
    "TRAFFIC STOP": 4793,
    "SIMPLE ASSAULT": 16472,
    "ARGUMENT FAMILY": 9558,
    "DUI": 15929,
    "MISC SERVICE CALL": 44566,
    "TRAFFIC COMPLAINT": 7528,
    "LOUD PARTY": 853,
    "BURGLARY": 13332,
    "MISC PUB": 72404,
    "FOLLOW UP": 49474,
    "UNATTENDED DEATH": 19192,
    "ICF/SCF": 8738,
    "HARASSMENT": 14513,
    "THREATENING": 11285,
    "PROPERTY DAMAGE": 19898,
    "VEH TOWED": 44321,
    "ALARM CALL": 5397,
    "TRESPASS WARN": 11732,
    "NUISANCE COMPLAINT": 22163,
    "ARGUMENT": 15278,
    "MISSING PERSON CXL": 636,
    "MVC VEH TOWED": 21426,
    "MVC": 50678,
    "ROBBERY": 6037,
    "LIC PLATE THEFT": 2140,
    "AUTO THEFT RECOVERY": 16312,
    "IDENTITY THEFT": 2267,
    "OVERDUE RENTAL VEH": 404,
    "LOST PROPERTY": 7682,
    "TRAFFIC CONTROL DEVICE": 2057,
    "PARKING VIOLATION": 31670,
    "UEMV": 14787,
    "MEDICAL ASSIST": 8230,
    "THEFT": 48783,
    "BURGLARY VEH TAKEN": 625,
    "TRESPASS": 9749,
    "AUTO THEFT": 19150,
    "STALLED/HAZARD VEH": 5132,
    "ORDER VIOLATION": 7726,
    "PEDD/SOLIC NUISANCE": 63,
    "ANIMAL NOISE": 2114,
    "SUSP VEH": 2093,
    "DEFIB CALL": 3010,
    "RECKLESS ENDANGERING": 872,
    "AGGRAVATED ASSAULT": 10415,
    "MISSING PERSON": 3751,
    "WARRANT ARREST": 28579,
    "FOUND PROPERTY": 3310,
    "MISC CRIME OFFENSE": 8950,
    "DROPPED CALL": 2663,
    "ATTENDED DEATH": 1995,
    "RUNAWAY": 6273,
    "FRAUD": 12127,
    "FAMILY OFF/NEG": 29959,
    "COUNTERFEIT/FORGERY": 2394,
    "BURGLARY VEH CXL": 472,
    "TRO INITIAL": 655,
    "HAZARDOUS DRIVER": 2062,
    "STALLED VEH": 673,
    "WEAPONS": 2426,
    "CUSTODIAL INTERFERENCE": 930,
    "DISORDERLY CONDUCT": 4900,
    "SUSP PERSON": 4129,
    "DRUGS/NARCOTICS": 4902,
    "TRAFFIC INCIDENT": 2217,
    "GRAFFITI": 994,
    "JUVENILE NUISANCE": 689,
    "FIREWORKS VIOLATION": 2123,
    "RUNAWAY CXL": 5440,
    "DRUNK NUISANCE": 511,
    "NOISE COMPLAINT": 6903,
    "SEX ASSAULT": 3371,
    "CONSTRUCTION NOISE": 242,
    "ARGUMENT LANDLORD TENANT": 233,
    "LIQUOR LAW": 1870,
    "FIRE CALL": 3454,
    "OVERDUE RENTAL CXL": 335,
    "ATTEMPTED SUICIDE": 842,
    "RAPE": 2359,
    "KIDNAPPING": 476,
    "TRAFFIC ARREST/CITATION": 3093,
    "DRONE NUISANCE": 49,
    "INDECENT EXPOSURE": 1034,
    "LIC PLATE THEFT CXL": 209,
    "LPROP LIC PLATE": 401,
    "ARSON": 1076,
    "ROBBERY VEH CXL": 454,
    "FAMILY OFF/NEG WARN": 277,
    "DUST/ECOL NUISANCE": 64,
    "SMOKE/FIRE NUISANCE": 271,
    "ARGUMENT NON FAMILY": 193,
    "ROBBERY VEH TAKEN": 685,
    "DELINQUENT JUVENILE": 147,
    "HOLD UP ALARM": 94,
    "SUICIDE": 81,
    "VEH NOISE": 234,
    "TRUANCY": 230,
    "PROSTITUTION": 72,
    "EXTRADITION VIOLATION": 210,
    "LPROP LIC PLATE CXL": 18,
    "BOMB THREAT": 112,
    "ESCAPEE": 127,
    "ESCAPEE CXL": 91,
    "HOMICIDE": 711,
    "GAMBLING": 54,
    "AWOL": 7,
    "RESIDENCE CHECK": 1
  },
  "cityCount": {
    "ALA MOANA": 18624,
    "WAIKIKI": 72438,
    "KALIHI": 70548,
    "MOANALUA": 1947,
    "EWA BEACH": 42494,
    "MILILANI": 23309,
    "KAILUA": 33217,
    "AIEA": 34914,
    "LAIE": 4919,
    "HONOLULU": 63456,
    "WAIPAHU": 31593,
    "MAKIKI": 14415,
    "KAPOLEI": 27548,
    "PEARL CITY": 24850,
    "WAIANAE": 24127,
    "HAWAII KAI": 14117,
    "KAPAHULU": 9631,
    "WAIMANALO": 10195,
    "MAPUNAPUNA": 4936,
    "MAKAKILO": 7230,
    "AIRPORT": 7310,
    "KAHALA": 5694,
    "SUNSET": 7490,
    "KANEOHE": 34597,
    "MCCULLY": 31915,
    "KAIMUKI": 24265,
    "DOWNTOWN": 25916,
    "MANOA": 12484,
    "MAKAHA": 10913,
    "WAIALAE": 3230,
    "WAHIAWA": 23538,
    "MAILI": 8856,
    "KAHUKU": 6832,
    "AINA HAINA": 5332,
    "NANAKULI": 13974,
    "WAIPIO": 11018,
    "KAKAAKO": 3540,
    "SALT LAKE": 8299,
    "WAIALUA": 3584,
    "KAHALUU": 4439,
    "MOANALUA V": 6040,
    "KALAELOA": 5522,
    "NUUANU": 13501,
    "MOKULEIA": 3657,
    "HAUULA": 4230,
    "PUNALUU": 2522,
    "KUNIA": 1371,
    "KAAAWA": 3027,
    "HALEIWA": 8165,
    "PUNCHBOWL": 7773,
    "ALIAMANU": 2532,
    "MALOELAP": 173,
    "SCHOFIELD": 1818,
    "MOANALUA T": 572,
    "TRIPLER": 857,
    "IROQUOIS": 3218,
    "HALSEY T": 317,
    "MCBH": 1017,
    "AMR": 476,
    "JB PEARL": 527,
    "FT SHAFTER": 189,
    "PC PEN": 437,
    "FT DERUSSY": 963,
    "JB HICKAM": 635,
    "BELLOWS": 163,
    "\u0000": 1323,
    "HOKULANI": 147,
    "KAHUKU RNG": 15,
    "94 - NAME?": 392,
    "CATLIN PK": 160,
    "MCGREW PT": 97,
    "MILLER PK": 250,
    "RADFORD T": 440,
    "FORD ISL": 120,
    "\u00a0": 40,
    "HALE MOKU": 399,
    "HELEMANO": 347,
    "CAMP SMITH": 18,
    "SHAFT FLAT": 31,
    "MAKUA": 108,
    "MAKALAPA": 64,
    "RED HILL": 33,
    "NCTAMS PAC": 48,
    "HALAWA": 131,
    "MANANA": 54,
    "WHEELER": 1,
    "WHEELER AFB": 2,
    "WAIPIO PT": 4,
    "PUULOA": 10,
    "NAVMAG LLL": 15
  },
  "districtCount": {
    "District 1": 136373,
    "District 6": 73501,
    "District 5": 119768,
    "District 8": 144632,
    "District 2": 73209,
    "District 4": 105276,
    "District 3": 103873,
    "District 7": 104122,
    "\u00a0": 838,
    "Citywide": 86,
    "LE": 7
  }
}