{
  "incidentCount": {
    "SUSP CIRCUMSTANCE": 3554,
    "TRAFFIC STOP": 1080,
    "SIMPLE ASSAULT": 3152,
    "ARGUMENT FAMILY": 1866,
    "DUI": 3780,
    "MISC SERVICE CALL": 8975,
    "TRAFFIC COMPLAINT": 1758,
    "LOUD PARTY": 210,
    "BURGLARY": 2890,
    "MISC PUB": 15076,
    "FOLLOW UP": 10137,
    "UNATTENDED DEATH": 3346,
    "ICF/SCF": 1639,
    "HARASSMENT": 2849,
    "THREATENING": 2160,
    "PROPERTY DAMAGE": 4265,
    "VEH TOWED": 7464,
    "ALARM CALL": 1114,
    "TRESPASS WARN": 2606,
    "NUISANCE COMPLAINT": 4472,
    "ARGUMENT": 3057,
    "MISSING PERSON CXL": 147,
    "MVC VEH TOWED": 3958,
    "MVC": 9257,
    "ROBBERY": 1159,
    "LIC PLATE THEFT": 509,
    "AUTO THEFT RECOVERY": 3270,
    "IDENTITY THEFT": 540,
    "OVERDUE RENTAL VEH": 103,
    "LOST PROPERTY": 1475,
    "TRAFFIC CONTROL DEVICE": 595,
    "PARKING VIOLATION": 5479,
    "UEMV": 3602,
    "MEDICAL ASSIST": 1495,
    "THEFT": 10582,
    "BURGLARY VEH TAKEN": 185,
    "TRESPASS": 1646,
    "AUTO THEFT": 3646,
    "STALLED/HAZARD VEH": 910,
    "ORDER VIOLATION": 1517,
    "PEDD/SOLIC NUISANCE": 12,
    "ANIMAL NOISE": 399,
    "SUSP VEH": 424,
    "DEFIB CALL": 660,
    "RECKLESS ENDANGERING": 183,
    "AGGRAVATED ASSAULT": 1812,
    "MISSING PERSON": 800,
    "WARRANT ARREST": 5160,
    "FOUND PROPERTY": 635,
    "MISC CRIME OFFENSE": 1667,
    "DROPPED CALL": 474,
    "ATTENDED DEATH": 368,
    "RUNAWAY": 1428,
    "FRAUD": 2270,
    "FAMILY OFF/NEG": 5325,
    "COUNTERFEIT/FORGERY": 582,
    "BURGLARY VEH CXL": 156,
    "TRO INITIAL": 130,
    "HAZARDOUS DRIVER": 414,
    "STALLED VEH": 138,
    "WEAPONS": 398,
    "CUSTODIAL INTERFERENCE": 167,
    "DISORDERLY CONDUCT": 1000,
    "SUSP PERSON": 871,
    "DRUGS/NARCOTICS": 1051,
    "TRAFFIC INCIDENT": 423,
    "GRAFFITI": 264,
    "JUVENILE NUISANCE": 129,
    "FIREWORKS VIOLATION": 695,
    "RUNAWAY CXL": 1131,
    "DRUNK NUISANCE": 114,
    "NOISE COMPLAINT": 1286,
    "SEX ASSAULT": 675,
    "CONSTRUCTION NOISE": 46,
    "ARGUMENT LANDLORD TENANT": 53,
    "LIQUOR LAW": 342,
    "FIRE CALL": 591,
    "OVERDUE RENTAL CXL": 80,
    "ATTEMPTED SUICIDE": 144,
    "RAPE": 454,
    "KIDNAPPING": 64,
    "TRAFFIC ARREST/CITATION": 340,
    "DRONE NUISANCE": 4,
    "INDECENT EXPOSURE": 176,
    "LIC PLATE THEFT CXL": 40,
    "LPROP LIC PLATE": 106,
    "ARSON": 317,
    "ROBBERY VEH CXL": 76,
    "FAMILY OFF/NEG WARN": 40,
    "DUST/ECOL NUISANCE": 13,
    "SMOKE/FIRE NUISANCE": 83,
    "ARGUMENT NON FAMILY": 46,
    "ROBBERY VEH TAKEN": 120,
    "DELINQUENT JUVENILE": 27,
    "HOLD UP ALARM": 20,
    "SUICIDE": 29,
    "VEH NOISE": 39,
    "TRUANCY": 56,
    "PROSTITUTION": 30,
    "EXTRADITION VIOLATION": 12,
    "LPROP LIC PLATE CXL": 1,
    "BOMB THREAT": 9,
    "ESCAPEE": 16,
    "ESCAPEE CXL": 15,
    "HOMICIDE": 76
  },
  "cityCount": {
    "ALA MOANA": 3558,
    "WAIKIKI": 12874,
    "KALIHI": 14763,
    "MOANALUA": 320,
    "EWA BEACH": 8671,
    "MILILANI": 4690,
    "KAILUA": 6721,
    "AIEA": 7013,
    "LAIE": 972,
    "HONOLULU": 13458,
    "WAIPAHU": 6230,
    "MAKIKI": 3050,
    "KAPOLEI": 5660,
    "PEARL CITY": 5032,
    "WAIANAE": 4334,
    "HAWAII KAI": 2931,
    "KAPAHULU": 1771,
    "WAIMANALO": 1980,
    "MAPUNAPUNA": 1042,
    "MAKAKILO": 1540,
    "AIRPORT": 1426,
    "KAHALA": 1135,
    "SUNSET": 1641,
    "KANEOHE": 6855,
    "MCCULLY": 6256,
    "KAIMUKI": 4380,
    "DOWNTOWN": 5150,
    "MANOA": 2528,
    "MAKAHA": 2143,
    "WAIALAE": 630,
    "WAHIAWA": 4038,
    "MAILI": 1674,
    "KAHUKU": 1311,
    "AINA HAINA": 1045,
    "NANAKULI": 2848,
    "WAIPIO": 1993,
    "KAKAAKO": 632,
    "SALT LAKE": 1467,
    "WAIALUA": 758,
    "KAHALUU": 873,
    "MOANALUA V": 1132,
    "KALAELOA": 1019,
    "NUUANU": 2675,
    "MOKULEIA": 812,
    "HAUULA": 1008,
    "PUNALUU": 731,
    "KUNIA": 258,
    "KAAAWA": 620,
    "HALEIWA": 1704,
    "PUNCHBOWL": 1426,
    "ALIAMANU": 379,
    "MALOELAP": 7,
    "SCHOFIELD": 403,
    "MOANALUA T": 115,
    "TRIPLER": 139,
    "IROQUOIS": 655,
    "HALSEY T": 66,
    "MCBH": 188,
    "AMR": 146,
    "JB PEARL": 134,
    "FT SHAFTER": 42,
    "PC PEN": 133,
    "FT DERUSSY": 170,
    "JB HICKAM": 113,
    "BELLOWS": 38,
    "\u0000": 247,
    "HOKULANI": 20,
    "KAHUKU RNG": 2,
    "94 - NAME?": 62,
    "CATLIN PK": 25,
    "MCGREW PT": 7,
    "MILLER PK": 29,
    "RADFORD T": 59,
    "FORD ISL": 9,
    "\u00a0": 33,
    "HALE MOKU": 89,
    "HELEMANO": 41,
    "CAMP SMITH": 9,
    "SHAFT FLAT": 8,
    "MAKUA": 30,
    "MAKALAPA": 19,
    "RED HILL": 6,
    "NCTAMS PAC": 12,
    "HALAWA": 5,
    "MANANA": 13
  },
  "districtCount": {
    "District 1": 27787,
    "District 6": 13061,
    "District 5": 24074,
    "District 8": 28658,
    "District 2": 14348,
    "District 4": 21315,
    "District 3": 20606,
    "District 7": 20153,
    "\u00a0": 186,
    "Citywide": 42,
    "LE": 1
  }
}