{
  "incidentCount": {
    "SUSP CIRCUMSTANCE": 10638,
    "TRAFFIC STOP": 3024,
    "SIMPLE ASSAULT": 10204,
    "ARGUMENT FAMILY": 6051,
    "DUI": 10397,
    "MISC SERVICE CALL": 28943,
    "TRAFFIC COMPLAINT": 4790,
    "LOUD PARTY": 560,
    "BURGLARY": 9001,
    "MISC PUB": 47386,
    "FOLLOW UP": 31436,
    "UNATTENDED DEATH": 12372,
    "ICF/SCF": 5442,
    "HARASSMENT": 9291,
    "THREATENING": 6825,
    "PROPERTY DAMAGE": 12953,
    "VEH TOWED": 26774,
    "ALARM CALL": 3501,
    "TRESPASS WARN": 7488,
    "NUISANCE COMPLAINT": 14007,
    "ARGUMENT": 9757,
    "MISSING PERSON CXL": 422,
    "MVC VEH TOWED": 13300,
    "MVC": 31405,
    "ROBBERY": 3818,
    "LIC PLATE THEFT": 1475,
    "AUTO THEFT RECOVERY": 10684,
    "IDENTITY THEFT": 1466,
    "OVERDUE RENTAL VEH": 265,
    "LOST PROPERTY": 4857,
    "TRAFFIC CONTROL DEVICE": 1404,
    "PARKING VIOLATION": 19210,
    "UEMV": 9821,
    "MEDICAL ASSIST": 5023,
    "THEFT": 30871,
    "BURGLARY VEH TAKEN": 439,
    "TRESPASS": 5540,
    "AUTO THEFT": 12221,
    "STALLED/HAZARD VEH": 3148,
    "ORDER VIOLATION": 5001,
    "PEDD/SOLIC NUISANCE": 42,
    "ANIMAL NOISE": 1324,
    "SUSP VEH": 1391,
    "DEFIB CALL": 1978,
    "RECKLESS ENDANGERING": 478,
    "AGGRAVATED ASSAULT": 6203,
    "MISSING PERSON": 2468,
    "WARRANT ARREST": 16956,
    "FOUND PROPERTY": 2081,
    "MISC CRIME OFFENSE": 5133,
    "DROPPED CALL": 1550,
    "ATTENDED DEATH": 1200,
    "RUNAWAY": 3914,
    "FRAUD": 7385,
    "FAMILY OFF/NEG": 17916,
    "COUNTERFEIT/FORGERY": 1540,
    "BURGLARY VEH CXL": 358,
    "TRO INITIAL": 381,
    "HAZARDOUS DRIVER": 1257,
    "STALLED VEH": 421,
    "WEAPONS": 1531,
    "CUSTODIAL INTERFERENCE": 619,
    "DISORDERLY CONDUCT": 2894,
    "SUSP PERSON": 2668,
    "DRUGS/NARCOTICS": 3126,
    "TRAFFIC INCIDENT": 1392,
    "GRAFFITI": 704,
    "JUVENILE NUISANCE": 421,
    "FIREWORKS VIOLATION": 1765,
    "RUNAWAY CXL": 3298,
    "DRUNK NUISANCE": 348,
    "NOISE COMPLAINT": 4366,
    "SEX ASSAULT": 2003,
    "CONSTRUCTION NOISE": 169,
    "ARGUMENT LANDLORD TENANT": 125,
    "LIQUOR LAW": 1017,
    "FIRE CALL": 2226,
    "OVERDUE RENTAL CXL": 204,
    "ATTEMPTED SUICIDE": 517,
    "RAPE": 1422,
    "KIDNAPPING": 331,
    "TRAFFIC ARREST/CITATION": 1821,
    "DRONE NUISANCE": 37,
    "INDECENT EXPOSURE": 634,
    "LIC PLATE THEFT CXL": 146,
    "LPROP LIC PLATE": 290,
    "ARSON": 708,
    "ROBBERY VEH CXL": 270,
    "FAMILY OFF/NEG WARN": 155,
    "DUST/ECOL NUISANCE": 42,
    "SMOKE/FIRE NUISANCE": 182,
    "ARGUMENT NON FAMILY": 127,
    "ROBBERY VEH TAKEN": 326,
    "DELINQUENT JUVENILE": 86,
    "HOLD UP ALARM": 58,
    "SUICIDE": 56,
    "VEH NOISE": 146,
    "TRUANCY": 136,
    "PROSTITUTION": 36,
    "EXTRADITION VIOLATION": 104,
    "LPROP LIC PLATE CXL": 7,
    "BOMB THREAT": 63,
    "ESCAPEE": 75,
    "ESCAPEE CXL": 38,
    "HOMICIDE": 494,
    "GAMBLING": 40,
    "AWOL": 7,
    "RESIDENCE CHECK": 1
  },
  "cityCount": {
    "ALA MOANA": 11644,
    "WAIKIKI": 42651,
    "KALIHI": 46348,
    "MOANALUA": 977,
    "EWA BEACH": 27326,
    "MILILANI": 14610,
    "KAILUA": 21611,
    "AIEA": 22342,
    "LAIE": 3483,
    "HONOLULU": 39641,
    "WAIPAHU": 20268,
    "MAKIKI": 8460,
    "KAPOLEI": 16966,
    "PEARL CITY": 16188,
    "WAIANAE": 13830,
    "HAWAII KAI": 9067,
    "KAPAHULU": 6153,
    "WAIMANALO": 6674,
    "MAPUNAPUNA": 3483,
    "MAKAKILO": 4695,
    "AIRPORT": 4667,
    "KAHALA": 3519,
    "SUNSET": 5152,
    "KANEOHE": 21471,
    "MCCULLY": 19993,
    "KAIMUKI": 14863,
    "DOWNTOWN": 15797,
    "MANOA": 7737,
    "MAKAHA": 7184,
    "WAIALAE": 2083,
    "WAHIAWA": 14169,
    "MAILI": 5621,
    "KAHUKU": 4544,
    "AINA HAINA": 3253,
    "NANAKULI": 8681,
    "WAIPIO": 7147,
    "KAKAAKO": 2016,
    "SALT LAKE": 5182,
    "WAIALUA": 2371,
    "KAHALUU": 2754,
    "MOANALUA V": 3589,
    "KALAELOA": 3727,
    "NUUANU": 8914,
    "MOKULEIA": 2513,
    "HAUULA": 3032,
    "PUNALUU": 1735,
    "KUNIA": 846,
    "KAAAWA": 1990,
    "HALEIWA": 5422,
    "PUNCHBOWL": 4632,
    "ALIAMANU": 1535,
    "MALOELAP": 87,
    "SCHOFIELD": 1263,
    "MOANALUA T": 312,
    "TRIPLER": 511,
    "IROQUOIS": 2123,
    "HALSEY T": 201,
    "MCBH": 629,
    "AMR": 351,
    "JB PEARL": 332,
    "FT SHAFTER": 137,
    "PC PEN": 304,
    "FT DERUSSY": 556,
    "JB HICKAM": 349,
    "BELLOWS": 130,
    "\u0000": 744,
    "HOKULANI": 71,
    "KAHUKU RNG": 11,
    "94 - NAME?": 255,
    "CATLIN PK": 93,
    "MCGREW PT": 36,
    "MILLER PK": 146,
    "RADFORD T": 272,
    "FORD ISL": 70,
    "\u00a0": 38,
    "HALE MOKU": 243,
    "HELEMANO": 260,
    "CAMP SMITH": 11,
    "SHAFT FLAT": 28,
    "MAKUA": 87,
    "MAKALAPA": 39,
    "RED HILL": 15,
    "NCTAMS PAC": 19,
    "HALAWA": 81,
    "MANANA": 28,
    "WHEELER": 1,
    "WHEELER AFB": 2,
    "WAIPIO PT": 1,
    "PUULOA": 10,
    "NAVMAG LLL": 15
  },
  "districtCount": {
    "District 1": 83876,
    "District 6": 43297,
    "District 5": 77536,
    "District 8": 90571,
    "District 2": 46546,
    "District 4": 68081,
    "District 3": 66896,
    "District 7": 65014,
    "\u00a0": 544,
    "Citywide": 50,
    "LE": 6
  }
}