{
  "incidentCount": {
    "SUSP CIRCUMSTANCE": 431,
    "TRAFFIC STOP": 140,
    "SIMPLE ASSAULT": 351,
    "ARGUMENT FAMILY": 246,
    "DUI": 419,
    "MISC SERVICE CALL": 1052,
    "TRAFFIC COMPLAINT": 295,
    "LOUD PARTY": 37,
    "BURGLARY": 411,
    "MISC PUB": 1822,
    "FOLLOW UP": 1210,
    "UNATTENDED DEATH": 388,
    "ICF/SCF": 207,
    "HARASSMENT": 357,
    "THREATENING": 314,
    "PROPERTY DAMAGE": 652,
    "VEH TOWED": 982,
    "ALARM CALL": 147,
    "TRESPASS WARN": 393,
    "NUISANCE COMPLAINT": 530,
    "ARGUMENT": 387,
    "MISSING PERSON CXL": 14,
    "MVC VEH TOWED": 447,
    "MVC": 1116,
    "ROBBERY": 180,
    "LIC PLATE THEFT": 97,
    "AUTO THEFT RECOVERY": 443,
    "IDENTITY THEFT": 40,
    "OVERDUE RENTAL VEH": 9,
    "LOST PROPERTY": 147,
    "TRAFFIC CONTROL DEVICE": 90,
    "PARKING VIOLATION": 626,
    "UEMV": 506,
    "MEDICAL ASSIST": 166,
    "THEFT": 1549,
    "BURGLARY VEH TAKEN": 29,
    "TRESPASS": 196,
    "AUTO THEFT": 387,
    "STALLED/HAZARD VEH": 106,
    "ORDER VIOLATION": 143,
    "PEDD/SOLIC NUISANCE": 3,
    "ANIMAL NOISE": 45,
    "SUSP VEH": 58,
    "DEFIB CALL": 105,
    "RECKLESS ENDANGERING": 33,
    "AGGRAVATED ASSAULT": 243,
    "MISSING PERSON": 118,
    "WARRANT ARREST": 667,
    "FOUND PROPERTY": 91,
    "MISC CRIME OFFENSE": 166,
    "DROPPED CALL": 66,
    "ATTENDED DEATH": 43,
    "RUNAWAY": 101,
    "FRAUD": 287,
    "FAMILY OFF/NEG": 759,
    "COUNTERFEIT/FORGERY": 78,
    "BURGLARY VEH CXL": 38,
    "TRO INITIAL": 27,
    "HAZARDOUS DRIVER": 30,
    "STALLED VEH": 24,
    "WEAPONS": 63,
    "CUSTODIAL INTERFERENCE": 35,
    "DISORDERLY CONDUCT": 86,
    "SUSP PERSON": 90,
    "DRUGS/NARCOTICS": 135,
    "TRAFFIC INCIDENT": 43,
    "GRAFFITI": 39,
    "JUVENILE NUISANCE": 16,
    "FIREWORKS VIOLATION": 497,
    "RUNAWAY CXL": 88,
    "DRUNK NUISANCE": 10,
    "NOISE COMPLAINT": 168,
    "SEX ASSAULT": 48,
    "CONSTRUCTION NOISE": 10,
    "ARGUMENT LANDLORD TENANT": 8,
    "LIQUOR LAW": 15,
    "FIRE CALL": 81,
    "OVERDUE RENTAL CXL": 12,
    "ATTEMPTED SUICIDE": 20,
    "RAPE": 54,
    "KIDNAPPING": 1,
    "TRAFFIC ARREST/CITATION": 24,
    "DRONE NUISANCE": 1,
    "INDECENT EXPOSURE": 18,
    "LIC PLATE THEFT CXL": 2,
    "LPROP LIC PLATE": 11,
    "ARSON": 90,
    "ROBBERY VEH CXL": 7,
    "FAMILY OFF/NEG WARN": 2,
    "DUST/ECOL NUISANCE": 7,
    "SMOKE/FIRE NUISANCE": 22,
    "ARGUMENT NON FAMILY": 3,
    "ROBBERY VEH TAKEN": 1,
    "DELINQUENT JUVENILE": 1,
    "HOLD UP ALARM": 1
  },
  "cityCount": {
    "ALA MOANA": 415,
    "WAIKIKI": 1569,
    "KALIHI": 1870,
    "MOANALUA": 20,
    "EWA BEACH": 1144,
    "MILILANI": 594,
    "KAILUA": 950,
    "AIEA": 780,
    "LAIE": 95,
    "HONOLULU": 1517,
    "WAIPAHU": 800,
    "MAKIKI": 388,
    "KAPOLEI": 768,
    "PEARL CITY": 683,
    "WAIANAE": 668,
    "HAWAII KAI": 487,
    "KAPAHULU": 192,
    "WAIMANALO": 290,
    "MAPUNAPUNA": 76,
    "MAKAKILO": 172,
    "AIRPORT": 194,
    "KAHALA": 143,
    "SUNSET": 173,
    "KANEOHE": 1009,
    "MCCULLY": 875,
    "KAIMUKI": 624,
    "DOWNTOWN": 713,
    "MANOA": 306,
    "MAKAHA": 282,
    "WAIALAE": 116,
    "WAHIAWA": 513,
    "MAILI": 187,
    "KAHUKU": 148,
    "AINA HAINA": 142,
    "NANAKULI": 395,
    "WAIPIO": 269,
    "KAKAAKO": 53,
    "SALT LAKE": 172,
    "WAIALUA": 85,
    "KAHALUU": 169,
    "MOANALUA V": 89,
    "KALAELOA": 188,
    "NUUANU": 343,
    "MOKULEIA": 65,
    "HAUULA": 94,
    "PUNALUU": 81,
    "KUNIA": 53,
    "KAAAWA": 84,
    "HALEIWA": 177,
    "PUNCHBOWL": 211,
    "ALIAMANU": 24,
    "MALOELAP": 2,
    "SCHOFIELD": 45,
    "MOANALUA T": 8,
    "TRIPLER": 13,
    "IROQUOIS": 44,
    "HALSEY T": 4,
    "MCBH": 5,
    "AMR": 7,
    "JB PEARL": 11,
    "FT SHAFTER": 2,
    "PC PEN": 10,
    "FT DERUSSY": 21,
    "JB HICKAM": 13,
    "BELLOWS": 14,
    "\u0000": 34,
    "HOKULANI": 2,
    "KAHUKU RNG": 1,
    "94 - NAME?": 6,
    "CATLIN PK": 2,
    "MCGREW PT": 2,
    "MILLER PK": 7,
    "RADFORD T": 2,
    "FORD ISL": 3,
    "\u00a0": 33,
    "HALE MOKU": 5,
    "HELEMANO": 1,
    "CAMP SMITH": 1
  },
  "districtCount": {
    "District 1": 3361,
    "District 6": 1591,
    "District 5": 2862,
    "District 8": 3867,
    "District 2": 1697,
    "District 4": 2941,
    "District 3": 2558,
    "District 7": 2825,
    "\u00a0": 51
  }
}