{
  "incidentCount": {
    "SUSP CIRCUMSTANCE": 20213,
    "TRAFFIC STOP": 5633,
    "SIMPLE ASSAULT": 19516,
    "ARGUMENT FAMILY": 11229,
    "DUI": 18843,
    "MISC SERVICE CALL": 52318,
    "TRAFFIC COMPLAINT": 8979,
    "LOUD PARTY": 1013,
    "BURGLARY": 15619,
    "MISC PUB": 84279,
    "FOLLOW UP": 58790,
    "UNATTENDED DEATH": 22809,
    "ICF/SCF": 10439,
    "HARASSMENT": 17253,
    "THREATENING": 13308,
    "PROPERTY DAMAGE": 23266,
    "VEH TOWED": 53424,
    "ALARM CALL": 6402,
    "TRESPASS WARN": 14026,
    "NUISANCE COMPLAINT": 26294,
    "ARGUMENT": 17720,
    "MISSING PERSON CXL": 814,
    "MVC VEH TOWED": 25496,
    "MVC": 60315,
    "ROBBERY": 7027,
    "LIC PLATE THEFT": 2472,
    "AUTO THEFT RECOVERY": 18882,
    "IDENTITY THEFT": 2608,
    "OVERDUE RENTAL VEH": 505,
    "LOST PROPERTY": 9214,
    "TRAFFIC CONTROL DEVICE": 2294,
    "PARKING VIOLATION": 37548,
    "UEMV": 16913,
    "MEDICAL ASSIST": 9858,
    "THEFT": 56575,
    "BURGLARY VEH TAKEN": 733,
    "TRESPASS": 11752,
    "AUTO THEFT": 22408,
    "STALLED/HAZARD VEH": 6017,
    "ORDER VIOLATION": 9167,
    "PEDD/SOLIC NUISANCE": 73,
    "ANIMAL NOISE": 2512,
    "SUSP VEH": 2395,
    "DEFIB CALL": 3617,
    "RECKLESS ENDANGERING": 1052,
    "AGGRAVATED ASSAULT": 12461,
    "MISSING PERSON": 4541,
    "WARRANT ARREST": 34382,
    "FOUND PROPERTY": 3859,
    "MISC CRIME OFFENSE": 11727,
    "DROPPED CALL": 2981,
    "ATTENDED DEATH": 2394,
    "RUNAWAY": 7406,
    "FRAUD": 13727,
    "FAMILY OFF/NEG": 35297,
    "COUNTERFEIT/FORGERY": 2668,
    "BURGLARY VEH CXL": 535,
    "TRO INITIAL": 743,
    "HAZARDOUS DRIVER": 2519,
    "STALLED VEH": 804,
    "WEAPONS": 2849,
    "CUSTODIAL INTERFERENCE": 1113,
    "DISORDERLY CONDUCT": 5848,
    "SUSP PERSON": 4894,
    "DRUGS/NARCOTICS": 5844,
    "TRAFFIC INCIDENT": 2711,
    "GRAFFITI": 1105,
    "JUVENILE NUISANCE": 799,
    "FIREWORKS VIOLATION": 3061,
    "RUNAWAY CXL": 6618,
    "DRUNK NUISANCE": 567,
    "NOISE COMPLAINT": 8311,
    "SEX ASSAULT": 3928,
    "CONSTRUCTION NOISE": 291,
    "ARGUMENT LANDLORD TENANT": 279,
    "LIQUOR LAW": 2221,
    "FIRE CALL": 4072,
    "OVERDUE RENTAL CXL": 404,
    "ATTEMPTED SUICIDE": 1003,
    "RAPE": 2822,
    "KIDNAPPING": 507,
    "TRAFFIC ARREST/CITATION": 4187,
    "DRONE NUISANCE": 61,
    "INDECENT EXPOSURE": 1361,
    "LIC PLATE THEFT CXL": 256,
    "LPROP LIC PLATE": 459,
    "ARSON": 1260,
    "ROBBERY VEH CXL": 483,
    "FAMILY OFF/NEG WARN": 338,
    "DUST/ECOL NUISANCE": 74,
    "SMOKE/FIRE NUISANCE": 321,
    "ARGUMENT NON FAMILY": 228,
    "ROBBERY VEH TAKEN": 777,
    "DELINQUENT JUVENILE": 185,
    "HOLD UP ALARM": 116,
    "SUICIDE": 117,
    "VEH NOISE": 282,
    "TRUANCY": 297,
    "PROSTITUTION": 93,
    "EXTRADITION VIOLATION": 228,
    "LPROP LIC PLATE CXL": 19,
    "BOMB THREAT": 117,
    "ESCAPEE": 128,
    "ESCAPEE CXL": 91,
    "HOMICIDE": 757,
    "GAMBLING": 68,
    "AWOL": 8,
    "RESIDENCE CHECK": 1
  },
  "cityCount": {
    "ALA MOANA": 22245,
    "WAIKIKI": 85648,
    "KALIHI": 82404,
    "MOANALUA": 2348,
    "EWA BEACH": 49518,
    "MILILANI": 27673,
    "KAILUA": 39290,
    "AIEA": 40916,
    "LAIE": 5438,
    "HONOLULU": 75785,
    "WAIPAHU": 37613,
    "MAKIKI": 17322,
    "KAPOLEI": 32806,
    "PEARL CITY": 29824,
    "WAIANAE": 29295,
    "HAWAII KAI": 16724,
    "KAPAHULU": 11308,
    "WAIMANALO": 12062,
    "MAPUNAPUNA": 5748,
    "MAKAKILO": 8474,
    "AIRPORT": 8778,
    "KAHALA": 6773,
    "SUNSET": 8688,
    "KANEOHE": 40815,
    "MCCULLY": 37067,
    "KAIMUKI": 29083,
    "DOWNTOWN": 31702,
    "MANOA": 14824,
    "MAKAHA": 12959,
    "WAIALAE": 3884,
    "WAHIAWA": 27335,
    "MAILI": 10696,
    "KAHUKU": 7730,
    "AINA HAINA": 6213,
    "NANAKULI": 16715,
    "WAIPIO": 12985,
    "KAKAAKO": 4396,
    "SALT LAKE": 9887,
    "WAIALUA": 4136,
    "KAHALUU": 5223,
    "MOANALUA V": 7188,
    "KALAELOA": 6502,
    "NUUANU": 15855,
    "MOKULEIA": 4215,
    "HAUULA": 4806,
    "PUNALUU": 2856,
    "KUNIA": 1646,
    "KAAAWA": 3434,
    "HALEIWA": 9417,
    "PUNCHBOWL": 9317,
    "ALIAMANU": 3009,
    "MALOELAP": 186,
    "SCHOFIELD": 2088,
    "MOANALUA T": 625,
    "TRIPLER": 989,
    "IROQUOIS": 3875,
    "HALSEY T": 379,
    "MCBH": 1264,
    "AMR": 586,
    "JB PEARL": 628,
    "FT SHAFTER": 217,
    "PC PEN": 520,
    "FT DERUSSY": 1201,
    "JB HICKAM": 808,
    "BELLOWS": 187,
    "\u0000": 1501,
    "HOKULANI": 191,
    "KAHUKU RNG": 20,
    "94 - NAME?": 456,
    "CATLIN PK": 239,
    "MCGREW PT": 103,
    "MILLER PK": 334,
    "RADFORD T": 484,
    "FORD ISL": 126,
    "\u00a0": 71,
    "HALE MOKU": 493,
    "HELEMANO": 438,
    "CAMP SMITH": 20,
    "SHAFT FLAT": 82,
    "MAKUA": 115,
    "MAKALAPA": 72,
    "RED HILL": 45,
    "NCTAMS PAC": 58,
    "HALAWA": 145,
    "MANANA": 65,
    "WHEELER": 1,
    "WHEELER AFB": 2,
    "WAIPIO PT": 8,
    "PUULOA": 10,
    "NAVMAG LLL": 15,
    "HONOLULU.": 1
  },
  "districtCount": {
    "District 1": 163856,
    "District 6": 86940,
    "District 5": 140854,
    "District 8": 171640,
    "District 2": 85569,
    "District 4": 123268,
    "District 3": 123068,
    "District 7": 122925,
    "\u00a0": 974,
    "Citywide": 90,
    "LE": 9,
    "Special Event 2": 30
  }
}