{
  "incidentCount": {
    "SUSP CIRCUMSTANCE": 8325,
    "TRAFFIC STOP": 2416,
    "SIMPLE ASSAULT": 7831,
    "ARGUMENT FAMILY": 4577,
    "DUI": 8582,
    "MISC SERVICE CALL": 22463,
    "TRAFFIC COMPLAINT": 3658,
    "LOUD PARTY": 434,
    "BURGLARY": 6685,
    "MISC PUB": 36484,
    "FOLLOW UP": 24217,
    "UNATTENDED DEATH": 9302,
    "ICF/SCF": 4169,
    "HARASSMENT": 7069,
    "THREATENING": 5246,
    "PROPERTY DAMAGE": 9980,
    "VEH TOWED": 19747,
    "ALARM CALL": 2662,
    "TRESPASS WARN": 5897,
    "NUISANCE COMPLAINT": 10811,
    "ARGUMENT": 7514,
    "MISSING PERSON CXL": 316,
    "MVC VEH TOWED": 9959,
    "MVC": 23782,
    "ROBBERY": 2909,
    "LIC PLATE THEFT": 1051,
    "AUTO THEFT RECOVERY": 7888,
    "IDENTITY THEFT": 1176,
    "OVERDUE RENTAL VEH": 220,
    "LOST PROPERTY": 3726,
    "TRAFFIC CONTROL DEVICE": 1026,
    "PARKING VIOLATION": 14741,
    "UEMV": 7550,
    "MEDICAL ASSIST": 3748,
    "THEFT": 24207,
    "BURGLARY VEH TAKEN": 361,
    "TRESPASS": 4229,
    "AUTO THEFT": 9047,
    "STALLED/HAZARD VEH": 2371,
    "ORDER VIOLATION": 3883,
    "PEDD/SOLIC NUISANCE": 26,
    "ANIMAL NOISE": 979,
    "SUSP VEH": 1048,
    "DEFIB CALL": 1516,
    "RECKLESS ENDANGERING": 358,
    "AGGRAVATED ASSAULT": 4812,
    "MISSING PERSON": 1949,
    "WARRANT ARREST": 12915,
    "FOUND PROPERTY": 1594,
    "MISC CRIME OFFENSE": 4021,
    "DROPPED CALL": 1162,
    "ATTENDED DEATH": 912,
    "RUNAWAY": 2991,
    "FRAUD": 5632,
    "FAMILY OFF/NEG": 13353,
    "COUNTERFEIT/FORGERY": 1143,
    "BURGLARY VEH CXL": 316,
    "TRO INITIAL": 303,
    "HAZARDOUS DRIVER": 953,
    "STALLED VEH": 316,
    "WEAPONS": 1131,
    "CUSTODIAL INTERFERENCE": 478,
    "DISORDERLY CONDUCT": 2286,
    "SUSP PERSON": 2124,
    "DRUGS/NARCOTICS": 2492,
    "TRAFFIC INCIDENT": 1079,
    "GRAFFITI": 591,
    "JUVENILE NUISANCE": 308,
    "FIREWORKS VIOLATION": 1048,
    "RUNAWAY CXL": 2608,
    "DRUNK NUISANCE": 278,
    "NOISE COMPLAINT": 3312,
    "SEX ASSAULT": 1595,
    "CONSTRUCTION NOISE": 119,
    "ARGUMENT LANDLORD TENANT": 100,
    "LIQUOR LAW": 745,
    "FIRE CALL": 1689,
    "OVERDUE RENTAL CXL": 162,
    "ATTEMPTED SUICIDE": 432,
    "RAPE": 1026,
    "KIDNAPPING": 282,
    "TRAFFIC ARREST/CITATION": 1379,
    "DRONE NUISANCE": 28,
    "INDECENT EXPOSURE": 440,
    "LIC PLATE THEFT CXL": 81,
    "LPROP LIC PLATE": 230,
    "ARSON": 528,
    "ROBBERY VEH CXL": 153,
    "FAMILY OFF/NEG WARN": 130,
    "DUST/ECOL NUISANCE": 34,
    "SMOKE/FIRE NUISANCE": 159,
    "ARGUMENT NON FAMILY": 97,
    "ROBBERY VEH TAKEN": 239,
    "DELINQUENT JUVENILE": 67,
    "HOLD UP ALARM": 34,
    "SUICIDE": 44,
    "VEH NOISE": 115,
    "TRUANCY": 104,
    "PROSTITUTION": 35,
    "EXTRADITION VIOLATION": 76,
    "LPROP LIC PLATE CXL": 4,
    "BOMB THREAT": 47,
    "ESCAPEE": 34,
    "ESCAPEE CXL": 27,
    "HOMICIDE": 383,
    "GAMBLING": 36,
    "AWOL": 7,
    "RESIDENCE CHECK": 1
  },
  "cityCount": {
    "ALA MOANA": 8948,
    "WAIKIKI": 32339,
    "KALIHI": 35489,
    "MOANALUA": 732,
    "EWA BEACH": 20904,
    "MILILANI": 11155,
    "KAILUA": 16512,
    "AIEA": 17060,
    "LAIE": 2823,
    "HONOLULU": 30651,
    "WAIPAHU": 15474,
    "MAKIKI": 6419,
    "KAPOLEI": 13015,
    "PEARL CITY": 12242,
    "WAIANAE": 10606,
    "HAWAII KAI": 7113,
    "KAPAHULU": 4587,
    "WAIMANALO": 5212,
    "MAPUNAPUNA": 2758,
    "MAKAKILO": 3698,
    "AIRPORT": 3583,
    "KAHALA": 2551,
    "SUNSET": 3972,
    "KANEOHE": 16587,
    "MCCULLY": 14891,
    "KAIMUKI": 10974,
    "DOWNTOWN": 12400,
    "MANOA": 5950,
    "MAKAHA": 5604,
    "WAIALAE": 1552,
    "WAHIAWA": 10570,
    "MAILI": 4337,
    "KAHUKU": 3563,
    "AINA HAINA": 2445,
    "NANAKULI": 6557,
    "WAIPIO": 5261,
    "KAKAAKO": 1590,
    "SALT LAKE": 3965,
    "WAIALUA": 1764,
    "KAHALUU": 2255,
    "MOANALUA V": 2739,
    "KALAELOA": 2912,
    "NUUANU": 6822,
    "MOKULEIA": 2057,
    "HAUULA": 2511,
    "PUNALUU": 1447,
    "KUNIA": 607,
    "KAAAWA": 1548,
    "HALEIWA": 4193,
    "PUNCHBOWL": 3350,
    "ALIAMANU": 1049,
    "MALOELAP": 58,
    "SCHOFIELD": 970,
    "MOANALUA T": 244,
    "TRIPLER": 449,
    "IROQUOIS": 1622,
    "HALSEY T": 114,
    "MCBH": 528,
    "AMR": 318,
    "JB PEARL": 286,
    "FT SHAFTER": 124,
    "PC PEN": 233,
    "FT DERUSSY": 448,
    "JB HICKAM": 266,
    "BELLOWS": 74,
    "\u0000": 587,
    "HOKULANI": 57,
    "KAHUKU RNG": 8,
    "94 - NAME?": 197,
    "CATLIN PK": 72,
    "MCGREW PT": 22,
    "MILLER PK": 95,
    "RADFORD T": 201,
    "FORD ISL": 32,
    "\u00a0": 38,
    "HALE MOKU": 156,
    "HELEMANO": 153,
    "CAMP SMITH": 11,
    "SHAFT FLAT": 19,
    "MAKUA": 85,
    "MAKALAPA": 33,
    "RED HILL": 11,
    "NCTAMS PAC": 17,
    "HALAWA": 46,
    "MANANA": 24,
    "WHEELER": 1,
    "WHEELER AFB": 2,
    "WAIPIO PT": 1,
    "PUULOA": 10
  },
  "districtCount": {
    "District 1": 64648,
    "District 6": 32860,
    "District 5": 59346,
    "District 8": 69531,
    "District 2": 35465,
    "District 4": 53093,
    "District 3": 50757,
    "District 7": 48780,
    "\u00a0": 420,
    "Citywide": 50,
    "LE": 5
  }
}