{
  "incidentCount": {
    "SUSP CIRCUMSTANCE": 3430,
    "TRAFFIC STOP": 1044,
    "SIMPLE ASSAULT": 3075,
    "ARGUMENT FAMILY": 1806,
    "DUI": 3750,
    "MISC SERVICE CALL": 8632,
    "TRAFFIC COMPLAINT": 1735,
    "LOUD PARTY": 204,
    "BURGLARY": 2823,
    "MISC PUB": 14615,
    "FOLLOW UP": 9722,
    "UNATTENDED DEATH": 3258,
    "ICF/SCF": 1591,
    "HARASSMENT": 2793,
    "THREATENING": 2072,
    "PROPERTY DAMAGE": 4042,
    "VEH TOWED": 7231,
    "ALARM CALL": 1078,
    "TRESPASS WARN": 2523,
    "NUISANCE COMPLAINT": 4337,
    "ARGUMENT": 2991,
    "MISSING PERSON CXL": 141,
    "MVC VEH TOWED": 3832,
    "MVC": 8940,
    "ROBBERY": 1144,
    "LIC PLATE THEFT": 495,
    "AUTO THEFT RECOVERY": 3158,
    "IDENTITY THEFT": 530,
    "OVERDUE RENTAL VEH": 102,
    "LOST PROPERTY": 1440,
    "TRAFFIC CONTROL DEVICE": 592,
    "PARKING VIOLATION": 5289,
    "UEMV": 3515,
    "MEDICAL ASSIST": 1453,
    "THEFT": 10256,
    "BURGLARY VEH TAKEN": 181,
    "TRESPASS": 1605,
    "AUTO THEFT": 3539,
    "STALLED/HAZARD VEH": 886,
    "ORDER VIOLATION": 1460,
    "PEDD/SOLIC NUISANCE": 11,
    "ANIMAL NOISE": 387,
    "SUSP VEH": 411,
    "DEFIB CALL": 639,
    "RECKLESS ENDANGERING": 178,
    "AGGRAVATED ASSAULT": 1749,
    "MISSING PERSON": 779,
    "WARRANT ARREST": 5025,
    "FOUND PROPERTY": 601,
    "MISC CRIME OFFENSE": 1608,
    "DROPPED CALL": 460,
    "ATTENDED DEATH": 356,
    "RUNAWAY": 1402,
    "FRAUD": 2194,
    "FAMILY OFF/NEG": 5155,
    "COUNTERFEIT/FORGERY": 566,
    "BURGLARY VEH CXL": 156,
    "TRO INITIAL": 126,
    "HAZARDOUS DRIVER": 394,
    "STALLED VEH": 133,
    "WEAPONS": 370,
    "CUSTODIAL INTERFERENCE": 167,
    "DISORDERLY CONDUCT": 951,
    "SUSP PERSON": 847,
    "DRUGS/NARCOTICS": 1014,
    "TRAFFIC INCIDENT": 413,
    "GRAFFITI": 261,
    "JUVENILE NUISANCE": 123,
    "FIREWORKS VIOLATION": 692,
    "RUNAWAY CXL": 1096,
    "DRUNK NUISANCE": 110,
    "NOISE COMPLAINT": 1258,
    "SEX ASSAULT": 653,
    "CONSTRUCTION NOISE": 43,
    "ARGUMENT LANDLORD TENANT": 51,
    "LIQUOR LAW": 341,
    "FIRE CALL": 583,
    "OVERDUE RENTAL CXL": 78,
    "ATTEMPTED SUICIDE": 141,
    "RAPE": 441,
    "KIDNAPPING": 49,
    "TRAFFIC ARREST/CITATION": 322,
    "DRONE NUISANCE": 4,
    "INDECENT EXPOSURE": 175,
    "LIC PLATE THEFT CXL": 35,
    "LPROP LIC PLATE": 105,
    "ARSON": 297,
    "ROBBERY VEH CXL": 74,
    "FAMILY OFF/NEG WARN": 40,
    "DUST/ECOL NUISANCE": 13,
    "SMOKE/FIRE NUISANCE": 83,
    "ARGUMENT NON FAMILY": 45,
    "ROBBERY VEH TAKEN": 117,
    "DELINQUENT JUVENILE": 21,
    "HOLD UP ALARM": 20,
    "SUICIDE": 28,
    "VEH NOISE": 35,
    "TRUANCY": 53,
    "PROSTITUTION": 30,
    "EXTRADITION VIOLATION": 12,
    "LPROP LIC PLATE CXL": 1,
    "BOMB THREAT": 9,
    "ESCAPEE": 16,
    "ESCAPEE CXL": 3,
    "HOMICIDE": 76
  },
  "cityCount": {
    "ALA MOANA": 3451,
    "WAIKIKI": 12514,
    "KALIHI": 14294,
    "MOANALUA": 304,
    "EWA BEACH": 8412,
    "MILILANI": 4551,
    "KAILUA": 6494,
    "AIEA": 6828,
    "LAIE": 953,
    "HONOLULU": 13093,
    "WAIPAHU": 5997,
    "MAKIKI": 2915,
    "KAPOLEI": 5510,
    "PEARL CITY": 4916,
    "WAIANAE": 4232,
    "HAWAII KAI": 2876,
    "KAPAHULU": 1679,
    "WAIMANALO": 1909,
    "MAPUNAPUNA": 984,
    "MAKAKILO": 1481,
    "AIRPORT": 1395,
    "KAHALA": 1083,
    "SUNSET": 1604,
    "KANEOHE": 6618,
    "MCCULLY": 6047,
    "KAIMUKI": 4248,
    "DOWNTOWN": 4960,
    "MANOA": 2447,
    "MAKAHA": 2094,
    "WAIALAE": 619,
    "WAHIAWA": 3872,
    "MAILI": 1617,
    "KAHUKU": 1253,
    "AINA HAINA": 1025,
    "NANAKULI": 2772,
    "WAIPIO": 1902,
    "KAKAAKO": 621,
    "SALT LAKE": 1404,
    "WAIALUA": 749,
    "KAHALUU": 841,
    "MOANALUA V": 1084,
    "KALAELOA": 1005,
    "NUUANU": 2603,
    "MOKULEIA": 781,
    "HAUULA": 979,
    "PUNALUU": 714,
    "KUNIA": 256,
    "KAAAWA": 590,
    "HALEIWA": 1640,
    "PUNCHBOWL": 1374,
    "ALIAMANU": 364,
    "MALOELAP": 7,
    "SCHOFIELD": 392,
    "MOANALUA T": 102,
    "TRIPLER": 139,
    "IROQUOIS": 639,
    "HALSEY T": 64,
    "MCBH": 182,
    "AMR": 141,
    "JB PEARL": 130,
    "FT SHAFTER": 41,
    "PC PEN": 133,
    "FT DERUSSY": 162,
    "JB HICKAM": 113,
    "BELLOWS": 38,
    "\u0000": 243,
    "HOKULANI": 20,
    "KAHUKU RNG": 2,
    "94 - NAME?": 55,
    "CATLIN PK": 25,
    "MCGREW PT": 7,
    "MILLER PK": 28,
    "RADFORD T": 53,
    "FORD ISL": 7,
    "\u00a0": 33,
    "HALE MOKU": 85,
    "HELEMANO": 39,
    "CAMP SMITH": 9,
    "SHAFT FLAT": 8,
    "MAKUA": 30,
    "MAKALAPA": 19,
    "RED HILL": 6,
    "NCTAMS PAC": 12,
    "HALAWA": 5,
    "MANANA": 13
  },
  "districtCount": {
    "District 1": 26908,
    "District 6": 12693,
    "District 5": 23270,
    "District 8": 27874,
    "District 2": 13881,
    "District 4": 20587,
    "District 3": 19977,
    "District 7": 19521,
    "\u00a0": 182,
    "Citywide": 42,
    "LE": 1
  }
}