{
  "incidentCount": {
    "SUSP CIRCUMSTANCE": 6771,
    "TRAFFIC STOP": 1883,
    "SIMPLE ASSAULT": 5989,
    "ARGUMENT FAMILY": 3643,
    "DUI": 7156,
    "MISC SERVICE CALL": 17738,
    "TRAFFIC COMPLAINT": 2959,
    "LOUD PARTY": 352,
    "BURGLARY": 5305,
    "MISC PUB": 28544,
    "FOLLOW UP": 19113,
    "UNATTENDED DEATH": 7199,
    "ICF/SCF": 3295,
    "HARASSMENT": 5503,
    "THREATENING": 4100,
    "PROPERTY DAMAGE": 8010,
    "VEH TOWED": 15288,
    "ALARM CALL": 2165,
    "TRESPASS WARN": 4591,
    "NUISANCE COMPLAINT": 8543,
    "ARGUMENT": 5787,
    "MISSING PERSON CXL": 247,
    "MVC VEH TOWED": 7661,
    "MVC": 18238,
    "ROBBERY": 2198,
    "LIC PLATE THEFT": 868,
    "AUTO THEFT RECOVERY": 6208,
    "IDENTITY THEFT": 996,
    "OVERDUE RENTAL VEH": 186,
    "LOST PROPERTY": 3066,
    "TRAFFIC CONTROL DEVICE": 889,
    "PARKING VIOLATION": 11370,
    "UEMV": 6131,
    "MEDICAL ASSIST": 2969,
    "THEFT": 19114,
    "BURGLARY VEH TAKEN": 302,
    "TRESPASS": 3260,
    "AUTO THEFT": 7047,
    "STALLED/HAZARD VEH": 1817,
    "ORDER VIOLATION": 2849,
    "PEDD/SOLIC NUISANCE": 18,
    "ANIMAL NOISE": 737,
    "SUSP VEH": 787,
    "DEFIB CALL": 1217,
    "RECKLESS ENDANGERING": 286,
    "AGGRAVATED ASSAULT": 3697,
    "MISSING PERSON": 1541,
    "WARRANT ARREST": 10050,
    "FOUND PROPERTY": 1217,
    "MISC CRIME OFFENSE": 3288,
    "DROPPED CALL": 934,
    "ATTENDED DEATH": 724,
    "RUNAWAY": 2374,
    "FRAUD": 4334,
    "FAMILY OFF/NEG": 10385,
    "COUNTERFEIT/FORGERY": 1004,
    "BURGLARY VEH CXL": 225,
    "TRO INITIAL": 245,
    "HAZARDOUS DRIVER": 752,
    "STALLED VEH": 247,
    "WEAPONS": 869,
    "CUSTODIAL INTERFERENCE": 368,
    "DISORDERLY CONDUCT": 1795,
    "SUSP PERSON": 1636,
    "DRUGS/NARCOTICS": 1965,
    "TRAFFIC INCIDENT": 844,
    "GRAFFITI": 513,
    "JUVENILE NUISANCE": 248,
    "FIREWORKS VIOLATION": 921,
    "RUNAWAY CXL": 2070,
    "DRUNK NUISANCE": 207,
    "NOISE COMPLAINT": 2624,
    "SEX ASSAULT": 1209,
    "CONSTRUCTION NOISE": 94,
    "ARGUMENT LANDLORD TENANT": 74,
    "LIQUOR LAW": 565,
    "FIRE CALL": 1223,
    "OVERDUE RENTAL CXL": 143,
    "ATTEMPTED SUICIDE": 325,
    "RAPE": 784,
    "KIDNAPPING": 229,
    "TRAFFIC ARREST/CITATION": 1097,
    "DRONE NUISANCE": 20,
    "INDECENT EXPOSURE": 362,
    "LIC PLATE THEFT CXL": 54,
    "LPROP LIC PLATE": 196,
    "ARSON": 454,
    "ROBBERY VEH CXL": 151,
    "FAMILY OFF/NEG WARN": 123,
    "DUST/ECOL NUISANCE": 26,
    "SMOKE/FIRE NUISANCE": 136,
    "ARGUMENT NON FAMILY": 80,
    "ROBBERY VEH TAKEN": 207,
    "DELINQUENT JUVENILE": 54,
    "HOLD UP ALARM": 29,
    "SUICIDE": 33,
    "VEH NOISE": 74,
    "TRUANCY": 66,
    "PROSTITUTION": 32,
    "EXTRADITION VIOLATION": 51,
    "LPROP LIC PLATE CXL": 2,
    "BOMB THREAT": 14,
    "ESCAPEE": 34,
    "ESCAPEE CXL": 27,
    "HOMICIDE": 209,
    "GAMBLING": 36,
    "AWOL": 7
  },
  "cityCount": {
    "ALA MOANA": 6975,
    "WAIKIKI": 25444,
    "KALIHI": 28125,
    "MOANALUA": 562,
    "EWA BEACH": 16156,
    "MILILANI": 8733,
    "KAILUA": 13069,
    "AIEA": 13443,
    "LAIE": 2207,
    "HONOLULU": 24663,
    "WAIPAHU": 12194,
    "MAKIKI": 5162,
    "KAPOLEI": 10249,
    "PEARL CITY": 9677,
    "WAIANAE": 8330,
    "HAWAII KAI": 5633,
    "KAPAHULU": 3447,
    "WAIMANALO": 4034,
    "MAPUNAPUNA": 2237,
    "MAKAKILO": 2925,
    "AIRPORT": 2860,
    "KAHALA": 1993,
    "SUNSET": 3139,
    "KANEOHE": 13242,
    "MCCULLY": 11588,
    "KAIMUKI": 8393,
    "DOWNTOWN": 9564,
    "MANOA": 4575,
    "MAKAHA": 4399,
    "WAIALAE": 1188,
    "WAHIAWA": 8020,
    "MAILI": 3359,
    "KAHUKU": 2827,
    "AINA HAINA": 1947,
    "NANAKULI": 5166,
    "WAIPIO": 3981,
    "KAKAAKO": 1244,
    "SALT LAKE": 2987,
    "WAIALUA": 1347,
    "KAHALUU": 1846,
    "MOANALUA V": 2114,
    "KALAELOA": 2325,
    "NUUANU": 5235,
    "MOKULEIA": 1552,
    "HAUULA": 2089,
    "PUNALUU": 1196,
    "KUNIA": 494,
    "KAAAWA": 1163,
    "HALEIWA": 3266,
    "PUNCHBOWL": 2596,
    "ALIAMANU": 779,
    "MALOELAP": 22,
    "SCHOFIELD": 732,
    "MOANALUA T": 177,
    "TRIPLER": 349,
    "IROQUOIS": 1251,
    "HALSEY T": 96,
    "MCBH": 408,
    "AMR": 274,
    "JB PEARL": 236,
    "FT SHAFTER": 100,
    "PC PEN": 213,
    "FT DERUSSY": 361,
    "JB HICKAM": 217,
    "BELLOWS": 71,
    "\u0000": 479,
    "HOKULANI": 52,
    "KAHUKU RNG": 4,
    "94 - NAME?": 132,
    "CATLIN PK": 42,
    "MCGREW PT": 17,
    "MILLER PK": 77,
    "RADFORD T": 171,
    "FORD ISL": 25,
    "\u00a0": 34,
    "HALE MOKU": 119,
    "HELEMANO": 80,
    "CAMP SMITH": 11,
    "SHAFT FLAT": 10,
    "MAKUA": 80,
    "MAKALAPA": 33,
    "RED HILL": 9,
    "NCTAMS PAC": 13,
    "HALAWA": 32,
    "MANANA": 22,
    "WHEELER": 1,
    "WHEELER AFB": 2,
    "WAIPIO PT": 1
  },
  "districtCount": {
    "District 1": 51229,
    "District 6": 25855,
    "District 5": 46627,
    "District 8": 54400,
    "District 2": 27351,
    "District 4": 42182,
    "District 3": 39918,
    "District 7": 37738,
    "\u00a0": 346,
    "Citywide": 42,
    "LE": 4
  }
}